Peripheral-Configuration-Distribution-Controller/rtl/peripheral_controller.v
module peripheral_controller (
    input  wire       clk,
    input  wire       reset,

    input  wire       start,
    input  wire [7:0] tx_data,
    input  wire       miso,

    output reg        mosi,
    output reg        sclk,
    output reg        cs,

    output reg [7:0]  rx_data,
    output reg        busy,
    output reg        done
);

    // --------------------------------------------------
    // Internal registers
    // --------------------------------------------------

    reg [7:0] tx_shift;
    reg [7:0] rx_shift;

    reg [3:0] bit_count;

    reg [1:0] clk_count;

    // --------------------------------------------------
    // SPI clock generation
    //
    // CPU clock is divided to generate SPI clock.
    // --------------------------------------------------

    always @(posedge clk) begin

        if (reset) begin

            tx_shift <= 8'b0;
            rx_shift <= 8'b0;

            bit_count <= 4'd0;
            clk_count <= 2'd0;

            mosi <= 1'b0;
            sclk <= 1'b0;
            cs   <= 1'b1;

            rx_data <= 8'b0;

            busy <= 1'b0;
            done <= 1'b0;

        end

        else begin

            done <= 1'b0;

            // --------------------------------------------------
            // Start a new SPI transaction
            // --------------------------------------------------

            if (start && !busy) begin

                tx_shift <= tx_data;
                rx_shift <= 8'b0;

                bit_count <= 4'd0;
                clk_count <= 2'd0;

                // First bit is placed on MOSI before
                // the first SPI clock edge.
                mosi <= tx_data[7];

                sclk <= 1'b0;
                cs   <= 1'b0;

                busy <= 1'b1;

            end

            // --------------------------------------------------
            // SPI transaction
            // --------------------------------------------------

            else if (busy) begin

                if (clk_count == 2'd1) begin

                    clk_count <= 2'd0;

                    // ------------------------------------------
                    // Rising SPI edge
                    // Sample MISO
                    // ------------------------------------------

                    if (sclk == 1'b0) begin

                        sclk <= 1'b1;

                        rx_shift <= {
                            rx_shift[6:0],
                            miso
                        };

                    end

                    // ------------------------------------------
                    // Falling SPI edge
                    // Shift TX data
                    // ------------------------------------------

                    else begin

                        sclk <= 1'b0;

                        if (bit_count == 4'd7) begin

                            // Transaction complete

                            rx_data <= rx_shift;

                            mosi <= 1'b0;

                            cs <= 1'b1;

                            busy <= 1'b0;

                            done <= 1'b1;

                        end

                        else begin

                            bit_count <= bit_count + 1'b1;

                            tx_shift <= {
                                tx_shift[6:0],
                                1'b0
                            };

                            mosi <= tx_shift[6];

                        end

                    end

                end

                else begin

                    clk_count <= clk_count + 1'b1;

                end

            end

        end

    end

endmodule

Peripheral-Configuration-Distribution-Controller/rtl/apb_peripheral_controller.v
module apb_peripheral_controller (
    input wire        pclk,
    input wire        presetn,

    input wire [7:0]  paddr,
    input wire        psel,
    input wire        penable,
    input wire        pwrite,
    input wire [31:0] pwdata,

    output wire [31:0] prdata,
    output wire        pready,
    output wire        pslverr,

    input wire        miso,
    output wire        mosi,
    output wire        sclk,
    output wire        cs,

    output wire        busy,
    output wire        done
);

    reg [31:0] tx_register;
    reg        start_pulse;

    wire [7:0] rx_data;
    wire       apb_write;

    assign apb_write = psel && penable && pwrite;

    assign pready  = 1'b1;
    assign pslverr = 1'b0;

    // APB register map
    // 0x00 : TX DATA
    // 0x04 : CONTROL
    // 0x08 : RX DATA
    // 0x0C : STATUS

    assign prdata =
        (paddr[3:2] == 2'b00) ? tx_register :
        (paddr[3:2] == 2'b01) ? {31'b0, busy} :
        (paddr[3:2] == 2'b10) ? {24'b0, rx_data} :
        (paddr[3:2] == 2'b11) ? {30'b0, done, busy} :
                                32'b0;

    // APB register/control logic
    always @(posedge pclk) begin
        if (!presetn) begin
            tx_register <= 32'b0;
            start_pulse <= 1'b0;
        end
        else begin
            // Start is a one-cycle pulse
            start_pulse <= 1'b0;

            if (apb_write) begin
                case (paddr[3:2])

                    // TX register
                    2'b00:
                        tx_register <= pwdata;

                    // Control register
                    // Bit 0 = START
                    2'b01:
                        if (pwdata[0])
                            start_pulse <= 1'b1;

                    default:
                        begin
                        end

                endcase
            end
        end
    end

    // SPI peripheral controller
    // This now uses the clock-divider-based implementation.
    peripheral_controller spi_controller (
        .clk      (pclk),
        .reset    (!presetn),

        .start    (start_pulse),
        .tx_data  (tx_register[7:0]),
        .miso     (miso),

        .mosi     (mosi),
        .sclk     (sclk),
        .cs       (cs),

        .rx_data  (rx_data),
        .busy     (busy),
        .done     (done)
    );

endmodule

Peripheral-Configuration-Distribution-Controller/tb/apb_peripheral_controller_tb.v
`timescale 1ns/1ps

module apb_peripheral_controller_tb;

    reg        pclk;
    reg        presetn;

    reg [7:0]  paddr;
    reg        psel;
    reg        penable;
    reg        pwrite;
    reg [31:0] pwdata;

    wire [31:0] prdata;
    wire        pready;
    wire        pslverr;

    reg         miso;

    wire        mosi;
    wire        sclk;
    wire        cs;

    wire        busy;
    wire        done;

    reg [7:0] slave_tx_data;
    reg [7:0] slave_rx_data;

    integer bit_count;
    integer errors;

    apb_peripheral_controller dut (
        .pclk    (pclk),
        .presetn (presetn),

        .paddr   (paddr),
        .psel    (psel),
        .penable (penable),
        .pwrite  (pwrite),
        .pwdata  (pwdata),

        .prdata  (prdata),
        .pready  (pready),
        .pslverr (pslverr),

        .miso    (miso),

        .mosi    (mosi),
        .sclk    (sclk),
        .cs      (cs),

        .busy    (busy),
        .done    (done)
    );

    always #5 pclk = ~pclk;

    always @(negedge sclk) begin
        if (!cs)
            miso <= slave_tx_data[7-bit_count];
    end

    always @(posedge sclk) begin
        if (!cs) begin

            slave_rx_data[7-bit_count] = mosi;

            if (bit_count < 7)
                bit_count = bit_count + 1;
            else
                bit_count = 0;

        end
    end

    task apb_write_task;
        input [7:0] addr;
        input [31:0] data;

        begin

            @(posedge pclk);
            paddr   <= addr;
            pwdata  <= data;
            pwrite  <= 1'b1;
            psel    <= 1'b1;
            penable <= 1'b0;

            @(posedge pclk);
            penable <= 1'b1;

            @(posedge pclk);
            psel    <= 1'b0;
            penable <= 1'b0;
            pwrite  <= 1'b0;

        end
    endtask

    task apb_read_task;
        input [7:0] addr;

        begin

            @(posedge pclk);
            paddr   <= addr;
            pwrite  <= 1'b0;
            psel    <= 1'b1;
            penable <= 1'b0;

            @(posedge pclk);
            penable <= 1'b1;

            @(posedge pclk);
            psel    <= 1'b0;
            penable <= 1'b0;

        end
    endtask

    initial begin

        $dumpfile("sim/waves/apb_peripheral_controller.vcd");
        $dumpvars(0, apb_peripheral_controller_tb);

        pclk    = 1'b0;
        presetn = 1'b0;

        paddr   = 8'b0;
        psel    = 1'b0;
        penable = 1'b0;
        pwrite  = 1'b0;
        pwdata  = 32'b0;

        miso = 1'b0;

        slave_tx_data = 8'b01100101;
        slave_rx_data = 8'b0;

        bit_count = 0;
        errors = 0;

        #20;
        presetn = 1'b1;

        if (pready !== 1'b1) begin
            $display("ERROR: PREADY");
            errors = errors + 1;
        end
        else
            $display("PASS: PREADY");

        if (pslverr !== 1'b0) begin
            $display("ERROR: PSLVERR");
            errors = errors + 1;
        end
        else
            $display("PASS: PSLVERR");

        // Write TX data
        apb_write_task(8'h00, 32'h000000A5);

        // Read TX data
        apb_read_task(8'h00);
        #1;

        if (prdata !== 32'h000000A5) begin
            $display("ERROR: TX register readback");
            errors = errors + 1;
        end
        else
            $display("PASS: TX register readback");

        // Start SPI
        apb_write_task(8'h04, 32'h00000001);

        // Wait for controller to become busy
        wait(busy == 1'b1);

        $display("PASS: SPI transaction started through APB");

        // Wait for transaction completion
        wait(done == 1'b1);

        #10;

        if (slave_rx_data !== 8'hA5) begin
            $display(
                "ERROR: SPI TX | Expected=%h | Got=%h",
                8'hA5,
                slave_rx_data
            );
            errors = errors + 1;
        end
        else
            $display("PASS: SPI TX through APB");

        // Read RX register
        apb_read_task(8'h08);
        #1;

        if (prdata[7:0] !== slave_tx_data) begin
            $display(
                "ERROR: SPI RX | Expected=%h | Got=%h",
                slave_tx_data,
                prdata[7:0]
            );
            errors = errors + 1;
        end
        else
            $display("PASS: SPI RX through APB");

        if (errors == 0) begin
            $display("--------------------------------");
            $display("APB PERIPHERAL CONTROLLER TEST PASSED");
            $display("--------------------------------");
        end
        else begin
            $display("--------------------------------");
            $display(
                "APB PERIPHERAL CONTROLLER TEST FAILED: %0d errors",
                errors
            );
            $display("--------------------------------");
        end

        $finish;

    end

endmodule

Peripheral-Configuration-Distribution-Controller/sim/waves/apb_peripheral_controller.vcd
$date
	Tue Sep 29 13:49:12 2026
$end
$version
	Icarus Verilog
$end
$timescale
	1ps
$end
$scope module apb_peripheral_controller_tb $end
$var wire 1 ! pready $end
$var wire 1 " pslverr $end
$var wire 1 # sclk $end
$var wire 32 $ prdata [31:0] $end
$var wire 1 % mosi $end
$var wire 1 & done $end
$var wire 1 ' cs $end
$var wire 1 ( busy $end
$var reg 1 ) miso $end
$var reg 8 * paddr [7:0] $end
$var reg 1 + pclk $end
$var reg 1 , penable $end
$var reg 1 - presetn $end
$var reg 1 . psel $end
$var reg 32 / pwdata [31:0] $end
$var reg 1 0 pwrite $end
$var reg 8 1 slave_rx_data [7:0] $end
$var reg 8 2 slave_tx_data [7:0] $end
$var integer 32 3 bit_count [31:0] $end
$var integer 32 4 errors [31:0] $end
$scope module dut $end
$var wire 1 5 apb_write $end
$var wire 1 ) miso $end
$var wire 8 6 paddr [7:0] $end
$var wire 1 + pclk $end
$var wire 1 , penable $end
$var wire 1 ! pready $end
$var wire 1 - presetn $end
$var wire 1 . psel $end
$var wire 1 " pslverr $end
$var wire 32 7 pwdata [31:0] $end
$var wire 1 0 pwrite $end
$var wire 1 # sclk $end
$var wire 8 8 rx_data [7:0] $end
$var wire 32 9 prdata [31:0] $end
$var wire 1 % mosi $end
$var wire 1 & done $end
$var wire 1 ' cs $end
$var wire 1 ( busy $end
$var reg 1 : start_pulse $end
$var reg 32 ; tx_register [31:0] $end
$scope module spi_controller $end
$var wire 1 + clk $end
$var wire 1 ) miso $end
$var wire 1 < reset $end
$var wire 1 : start $end
$var wire 8 = tx_data [7:0] $end
$var reg 4 > bit_count [3:0] $end
$var reg 1 ( busy $end
$var reg 2 ? clk_count [1:0] $end
$var reg 1 ' cs $end
$var reg 1 & done $end
$var reg 1 % mosi $end
$var reg 8 @ rx_data [7:0] $end
$var reg 8 A rx_shift [7:0] $end
$var reg 1 # sclk $end
$var reg 8 B tx_shift [7:0] $end
$upscope $end
$upscope $end
$scope task apb_read_task $end
$var reg 8 C addr [7:0] $end
$upscope $end
$scope task apb_write_task $end
$var reg 8 D addr [7:0] $end
$var reg 32 E data [31:0] $end
$upscope $end
$upscope $end
$enddefinitions $end
$comment Show the parameter values. $end
$dumpall
$end
#0
$dumpvars
bx E
bx D
bx C
bx B
bx A
bx @
bx ?
bx >
bx =
1<
bx ;
x:
bx 9
bx 8
b0 7
b0 6
05
b0 4
b0 3
b1100101 2
b0 1
00
b0 /
0.
0-
0,
0+
b0 *
0)
x(
x'
x&
x%
bx $
x#
0"
1!
$end
#5000
b0 $
b0 9
b0 =
0&
0(
b0 8
b0 @
1'
0#
0%
b0 ?
b0 >
b0 A
b0 B
0:
b0 ;
1+
#10000
0+
#15000
1+
#20000
0+
b10100101 E
b0 D
0<
1-
#25000
1.
10
b10100101 /
b10100101 7
1+
#30000
0+
#35000
15
1,
1+
#40000
0+
#45000
b10100101 $
b10100101 9
b10100101 =
05
b10100101 ;
00
0,
0.
b0 C
1+
#50000
0+
#55000
1.
1+
#60000
0+
#65000
1,
1+
#70000
0+
#75000
0,
0.
1+
#76000
b1 E
b100 D
#80000
0+
#85000
b0 $
b0 9
1.
10
b1 /
b1 7
b100 *
b100 6
1+
#90000
0+
#95000
15
1,
1+
#100000
0+
#105000
05
1:
00
0,
0.
1+
#110000
0+
#115000
b1 $
b1 9
0:
1(
0'
1%
b10100101 B
1+
#120000
0+
#125000
b1 ?
1+
#130000
0+
#135000
b1 3
b10000000 1
1#
b0 ?
1+
#140000
0+
#145000
b1 ?
1+
#150000
0+
#155000
1)
0%
b1001010 B
b1 >
0#
b0 ?
1+
#160000
0+
#165000
b1 ?
1+
#170000
0+
#175000
b10 3
b1 A
1#
b0 ?
1+
#180000
0+
#185000
b1 ?
1+
#190000
0+
#195000
1%
b10010100 B
b10 >
0#
b0 ?
1+
#200000
0+
#205000
b1 ?
1+
#210000
0+
#215000
b11 3
b10100000 1
b11 A
1#
b0 ?
1+
#220000
0+
#225000
b1 ?
1+
#230000
0+
#235000
0)
0%
b101000 B
b11 >
0#
b0 ?
1+
#240000
0+
#245000
b1 ?
1+
#250000
0+
#255000
b100 3
b110 A
1#
b0 ?
1+
#260000
0+
#265000
b1 ?
1+
#270000
0+
#275000
b1010000 B
b100 >
0#
b0 ?
1+
#280000
0+
#285000
b1 ?
1+
#290000
0+
#295000
b101 3
b1100 A
1#
b0 ?
1+
#300000
0+
#305000
b1 ?
1+
#310000
0+
#315000
1)
1%
b10100000 B
b101 >
0#
b0 ?
1+
#320000
0+
#325000
b1 ?
1+
#330000
0+
#335000
b110 3
b10100100 1
b11001 A
1#
b0 ?
1+
#340000
0+
#345000
b1 ?
1+
#350000
0+
#355000
0)
0%
b1000000 B
b110 >
0#
b0 ?
1+
#360000
0+
#365000
b1 ?
1+
#370000
0+
#375000
b111 3
b110010 A
1#
b0 ?
1+
#380000
0+
#385000
b1 ?
1+
#390000
0+
#395000
1)
1%
b10000000 B
b111 >
0#
b0 ?
1+
#400000
0+
#405000
b1 ?
1+
#410000
0+
#415000
b0 3
b10100101 1
b1100101 A
1#
b0 ?
1+
#420000
0+
#425000
b1 ?
1+
#430000
0+
#435000
b0 $
b0 9
1&
0(
1'
0%
b1100101 8
b1100101 @
0#
b0 ?
1+
#440000
0+
#445000
b1100101 $
b1100101 9
0&
1.
b1000 *
b1000 6
1+
b1000 C
#450000
0+
#455000
1,
1+
#460000
0+
#465000
0,
0.
1+
