Peripheral-Configuration-Distribution-Controller/rtl/apb_interface.v
module apb_interface #(
    parameter DATA_WIDTH = 32,
    parameter ADDR_WIDTH = 8
)(
    input  wire                  pclk,
    input  wire                  presetn,

    input  wire [ADDR_WIDTH-1:0] paddr,
    input  wire                  psel,
    input  wire                  penable,
    input  wire                  pwrite,

    input  wire [DATA_WIDTH-1:0] pwdata,

    output reg  [DATA_WIDTH-1:0] prdata,
    output wire                  pready,
    output wire                  pslverr
);

    reg [DATA_WIDTH-1:0] registers [0:3];

    assign pready  = 1'b1;
    assign pslverr = 1'b0;

    always @(posedge pclk) begin

        if (!presetn) begin

            prdata <= {DATA_WIDTH{1'b0}};

            registers[0] <= {DATA_WIDTH{1'b0}};
            registers[1] <= {DATA_WIDTH{1'b0}};
            registers[2] <= {DATA_WIDTH{1'b0}};
            registers[3] <= {DATA_WIDTH{1'b0}};

        end

        else if (psel && penable) begin

            if (pwrite) begin

                case (paddr[3:2])

                    2'b00: registers[0] <= pwdata;
                    2'b01: registers[1] <= pwdata;
                    2'b10: registers[2] <= pwdata;
                    2'b11: registers[3] <= pwdata;

                endcase

            end

            else begin

                case (paddr[3:2])

                    2'b00: prdata <= registers[0];
                    2'b01: prdata <= registers[1];
                    2'b10: prdata <= registers[2];
                    2'b11: prdata <= registers[3];

                endcase

            end

        end

    end

endmodule

Peripheral-Configuration-Distribution-Controller/tb/apb_interface_tb.v
`timescale 1ns/1ps

module apb_interface_tb;

    reg        pclk;
    reg        presetn;

    reg [7:0]  paddr;
    reg        psel;
    reg        penable;
    reg        pwrite;
    reg [31:0] pwdata;

    wire [31:0] prdata;
    wire        pready;
    wire        pslverr;

    integer errors;

    apb_interface uut (
        .pclk    (pclk),
        .presetn (presetn),
        .paddr   (paddr),
        .psel    (psel),
        .penable (penable),
        .pwrite  (pwrite),
        .pwdata  (pwdata),
        .prdata  (prdata),
        .pready  (pready),
        .pslverr (pslverr)
    );

    always #5 pclk = ~pclk;

    initial begin

        $dumpfile("sim/waves/apb_interface.vcd");
        $dumpvars(0, apb_interface_tb);

        pclk    = 1'b0;
        presetn = 1'b0;

        paddr   = 8'b0;
        psel    = 1'b0;
        penable = 1'b0;
        pwrite  = 1'b0;
        pwdata  = 32'b0;

        errors = 0;

        // ------------------------------------------------
        // Reset
        // ------------------------------------------------

        @(posedge pclk);
        #1;

        presetn = 1'b1;

        if (pready !== 1'b1) begin
            $display("ERROR: PREADY should be HIGH");
            errors = errors + 1;
        end
        else begin
            $display("PASS: PREADY is HIGH");
        end

        if (pslverr !== 1'b0) begin
            $display("ERROR: PSLVERR should be LOW");
            errors = errors + 1;
        end

        // ------------------------------------------------
        // APB WRITE
        // Address 0x00
        // ------------------------------------------------

        paddr   = 8'h00;
        pwdata  = 32'hA5A5_1234;
        pwrite  = 1'b1;
        psel    = 1'b1;

        // APB setup phase
        @(posedge pclk);
        #1;

        // APB access phase
        penable = 1'b1;

        @(posedge pclk);
        #1;

        psel    = 1'b0;
        penable = 1'b0;
        pwrite  = 1'b0;

        $display("PASS: APB write transaction completed");

        // ------------------------------------------------
        // APB READ
        // Address 0x00
        // ------------------------------------------------

        paddr   = 8'h00;
        pwrite  = 1'b0;
        psel    = 1'b1;

        // Setup phase
        @(posedge pclk);
        #1;

        // Access phase
        penable = 1'b1;

        @(posedge pclk);
        #1;

        if (prdata !== 32'hA5A5_1234) begin
            $display(
                "ERROR: APB read | Expected=%h | Got=%h",
                32'hA5A5_1234,
                prdata
            );
            errors = errors + 1;
        end
        else begin
            $display("PASS: APB read returned correct data");
        end

        psel    = 1'b0;
        penable = 1'b0;

        // ------------------------------------------------
        // Second register test
        // ------------------------------------------------

        paddr  = 8'h04;
        pwdata = 32'h1234_5678;
        pwrite = 1'b1;
        psel   = 1'b1;

        @(posedge pclk);
        #1;

        penable = 1'b1;

        @(posedge pclk);
        #1;

        psel    = 1'b0;
        penable = 1'b0;
        pwrite  = 1'b0;

        // Read second register

        paddr = 8'h04;
        psel  = 1'b1;

        @(posedge pclk);
        #1;

        penable = 1'b1;

        @(posedge pclk);
        #1;

        if (prdata !== 32'h1234_5678) begin
            $display(
                "ERROR: Second APB read | Expected=%h | Got=%h",
                32'h1234_5678,
                prdata
            );
            errors = errors + 1;
        end
        else begin
            $display("PASS: Second APB register verified");
        end

        // ------------------------------------------------
        // Final result
        // ------------------------------------------------

        if (errors == 0) begin
            $display("--------------------------------");
            $display("APB INTERFACE TEST PASSED");
            $display("--------------------------------");
        end
        else begin
            $display("--------------------------------");
            $display(
                "APB INTERFACE TEST FAILED: %0d errors",
                errors
            );
            $display("--------------------------------");
        end

        $finish;

    end

endmodule

Peripheral-Configuration-Distribution-Controller/sim/waves/apb_interface.vcd
$date
	Tue Sep 29 14:17:13 2026
$end
$version
	Icarus Verilog
$end
$timescale
	1ps
$end
$scope module apb_interface_tb $end
$var wire 1 ! pready $end
$var wire 1 " pslverr $end
$var wire 32 # prdata [31:0] $end
$var reg 8 $ paddr [7:0] $end
$var reg 1 % pclk $end
$var reg 1 & penable $end
$var reg 1 ' presetn $end
$var reg 1 ( psel $end
$var reg 32 ) pwdata [31:0] $end
$var reg 1 * pwrite $end
$var integer 32 + errors [31:0] $end
$scope module uut $end
$var wire 8 , paddr [7:0] $end
$var wire 1 % pclk $end
$var wire 1 & penable $end
$var wire 1 ! pready $end
$var wire 1 ' presetn $end
$var wire 1 ( psel $end
$var wire 1 " pslverr $end
$var wire 32 - pwdata [31:0] $end
$var wire 1 * pwrite $end
$var parameter 32 . ADDR_WIDTH $end
$var parameter 32 / DATA_WIDTH $end
$var reg 32 0 prdata [31:0] $end
$upscope $end
$upscope $end
$enddefinitions $end
$comment Show the parameter values. $end
$dumpall
b100000 /
b1000 .
$end
#0
$dumpvars
bx 0
b0 -
b0 ,
b0 +
0*
b0 )
0(
0'
0&
0%
b0 $
bx #
0"
1!
$end
#5000
b0 #
b0 0
1%
#6000
1(
1*
b10100101101001010001001000110100 )
b10100101101001010001001000110100 -
1'
#10000
0%
#15000
1%
#16000
1&
#20000
0%
#25000
1%
#26000
0*
0&
1(
#30000
0%
#35000
1%
#36000
1&
#40000
0%
#45000
b10100101101001010001001000110100 #
b10100101101001010001001000110100 0
1%
#46000
1*
b10010001101000101011001111000 )
b10010001101000101011001111000 -
b100 $
b100 ,
0&
1(
#50000
0%
#55000
1%
#56000
1&
#60000
0%
#65000
1%
#66000
0*
0&
1(
#70000
0%
#75000
1%
#76000
1&
#80000
0%
#85000
b10010001101000101011001111000 #
b10010001101000101011001111000 0
1%
