Peripheral-Configuration-Distribution-Controller/rtl/sipo.v
module sipo (
    input  wire       clk,
    input  wire       reset,
    input  wire       enable,
    input  wire       serial_in,
    output reg  [7:0] parallel_out,
    output reg        valid
);

    reg [7:0] shift_reg;
    reg [2:0] bit_count;

    always @(posedge clk) begin

        if (reset) begin
            shift_reg   <= 8'b0;
            parallel_out <= 8'b0;
            bit_count   <= 3'b0;
            valid       <= 1'b0;
        end

        else begin

            valid <= 1'b0;

            if (enable) begin

                if (bit_count < 3'd7) begin
                    shift_reg <= {serial_in, shift_reg[7:1]};
                    bit_count <= bit_count + 1'b1;
                end

                else begin
                    shift_reg <= {serial_in, shift_reg[7:1]};

                    parallel_out <= {serial_in, shift_reg[7:1]};

                    bit_count <= 3'b0;
                    valid <= 1'b1;
                end

            end

        end

    end

endmodule

Peripheral-Configuration-Distribution-Controller/rtl/piso.v
module piso (
    input wire       clk,
    input wire       reset,
    input wire       load,
    input wire       enable,

    input wire [7:0] parallel_in,

    output reg       serial_out,
    output reg       valid
);

    reg [7:0] shift_reg;
    reg [2:0] bit_count;

    always @(posedge clk) begin

        if (reset) begin

            shift_reg  <= 8'b0;
            bit_count  <= 3'b0;
            serial_out <= 1'b0;
            valid      <= 1'b0;

        end

        else begin

            valid <= 1'b0;

            // Load parallel data
            if (load) begin

                shift_reg  <= parallel_in;
                bit_count  <= 3'b0;
                serial_out <= parallel_in[0];

            end

            // Shift only when enabled
            else if (enable) begin

                if (bit_count < 3'd7) begin

                    shift_reg  <= shift_reg >> 1;
                    bit_count  <= bit_count + 1'b1;
                    serial_out <= shift_reg[1];

                end

                else begin

                    shift_reg  <= shift_reg >> 1;
                    bit_count  <= 3'b0;
                    serial_out <= shift_reg[7];
                    valid      <= 1'b1;

                end

            end

        end

    end

endmodule

Peripheral-Configuration-Distribution-Controller/rtl/clock_divider.v
module clock_divider (
    input  wire clk,
    input  wire reset,
    output reg  clk_out
);

    reg [1:0] count;

    always @(posedge clk) begin

        if (reset) begin
            count   <= 2'b00;
            clk_out <= 1'b0;
        end

        else begin

            if (count == 2'd1) begin
                count   <= 2'b00;
                clk_out <= ~clk_out;
            end

            else begin
                count <= count + 1'b1;
            end

        end

    end

endmodule

Peripheral-Configuration-Distribution-Controller/rtl/spi_master_top.v
module spi_master_top (
    input wire        clk,
    input wire        reset,
    input wire        start,
    input wire [7:0]  tx_data,
    input wire        miso,

    output wire       mosi,
    output reg        sclk,
    output wire       cs,
    output wire [7:0] rx_data,
    output wire       busy,
    output wire       done
);

    // ============================================================
    // Internal signals
    // ============================================================

    wire spi_clk;

    wire piso_serial;
    wire piso_valid;

    wire [7:0] sipo_parallel;
    wire       sipo_valid;

    reg piso_load;
    reg piso_enable;
    reg sipo_enable;

    reg [2:0] bit_count;

    reg active;
    reg done_reg;

    reg spi_clk_prev;

    // First rising edge must occur before PISO is shifted.
    reg first_sample_done;

    // ============================================================
    // Clock divider
    // ============================================================

    clock_divider clk_div (
        .clk(clk),
        .reset(reset),
        .clk_out(spi_clk)
    );

    // ============================================================
    // PISO
    // ============================================================

    piso tx_piso (
        .clk(clk),
        .reset(reset),
        .load(piso_load),
        .enable(piso_enable),
        .parallel_in(tx_data),
        .serial_out(piso_serial),
        .valid(piso_valid)
    );

    // ============================================================
    // SIPO
    // ============================================================

    sipo rx_sipo (
        .clk(clk),
        .reset(reset),
        .enable(sipo_enable),
        .serial_in(miso),
        .parallel_out(sipo_parallel),
        .valid(sipo_valid)
    );

    // ============================================================
    // Outputs
    // ============================================================

    assign mosi    = piso_serial;
    assign rx_data = sipo_parallel;

    assign busy = active;
    assign cs   = ~active;
    assign done = done_reg;

    // ============================================================
    // SPI controller
    // ============================================================

    always @(posedge clk) begin

        if (reset) begin

            piso_load       <= 1'b0;
            piso_enable     <= 1'b0;
            sipo_enable     <= 1'b0;

            bit_count       <= 3'd0;

            active          <= 1'b0;
            done_reg        <= 1'b0;

            spi_clk_prev    <= 1'b0;
            first_sample_done <= 1'b0;

            sclk            <= 1'b0;

        end

        else begin

            // ----------------------------------------------------
            // Default pulse signals
            // ----------------------------------------------------

            piso_load   <= 1'b0;
            piso_enable <= 1'b0;
            sipo_enable <= 1'b0;

            done_reg <= 1'b0;

            // ----------------------------------------------------
            // Start transaction
            // ----------------------------------------------------

            if (start && !active) begin

                // Load TX data into PISO.
                piso_load <= 1'b1;

                bit_count <= 3'd0;

                active <= 1'b1;

                sclk <= 1'b0;

                /*
                 * Synchronize the divider edge detector with its
                 * current state.
                 */
                spi_clk_prev <= spi_clk;

                /*
                 * Most important part:
                 * do not shift PISO until the first rising edge
                 * has sampled bit 0.
                 */
                first_sample_done <= 1'b0;

            end

            // ----------------------------------------------------
            // Active SPI transaction
            // ----------------------------------------------------

            else if (active) begin

                // Detect divider clock transition.
                if (spi_clk != spi_clk_prev) begin

                    // =================================================
                    // RISING EDGE
                    // =================================================

                    if (spi_clk == 1'b1) begin

                        /*
                         * Sample MISO.
                         *
                         * This is always the first SPI operation.
                         * Therefore PISO bit 0 cannot be lost.
                         */
                        sipo_enable <= 1'b1;

                        sclk <= 1'b1;

                        first_sample_done <= 1'b1;

                    end

                    // =================================================
                    // FALLING EDGE
                    // =================================================

                    else begin

                        sclk <= 1'b0;

                        /*
                         * Never shift before the first rising edge.
                         */
                        if (first_sample_done) begin

                            if (bit_count == 3'd7) begin

                                // Eight bits completed.
                                active   <= 1'b0;
                                done_reg <= 1'b1;

                            end

                            else begin

                                // Prepare next TX bit.
                                piso_enable <= 1'b1;

                                bit_count <= bit_count + 1'b1;

                            end

                        end

                    end

                end

                // Update divider history.
                spi_clk_prev <= spi_clk;

            end

            else begin

                sclk <= 1'b0;

            end

        end

    end

endmodule

Peripheral-Configuration-Distribution-Controller/rtl/apb_peripheral_controller.v
module apb_peripheral_controller (
    input wire        pclk,
    input wire        presetn,

    input wire [7:0]  paddr,
    input wire        psel,
    input wire        penable,
    input wire        pwrite,
    input wire [31:0] pwdata,

    output wire [31:0] prdata,
    output wire        pready,
    output wire        pslverr,

    input wire        miso,
    output wire        mosi,
    output wire        sclk,
    output wire        cs,

    output wire        busy,
    output wire        done
);

    reg [31:0] tx_register;
    reg        start_pulse;

    wire [7:0] rx_data;
    wire       apb_write;

    assign apb_write = psel && penable && pwrite;

    assign pready  = 1'b1;
    assign pslverr = 1'b0;

    // ------------------------------------------------------------
    // APB register map
    //
    // 0x00 : TX DATA
    // 0x04 : CONTROL
    //        bit 0 = START
    // 0x08 : RX DATA
    // 0x0C : STATUS
    //        bit 0 = BUSY
    //        bit 1 = DONE
    // ------------------------------------------------------------

    assign prdata =
        (paddr[3:2] == 2'b00) ? tx_register :
        (paddr[3:2] == 2'b01) ? {31'b0, busy} :
        (paddr[3:2] == 2'b10) ? {24'b0, rx_data} :
        (paddr[3:2] == 2'b11) ? {30'b0, done, busy} :
                                32'b0;


    // ------------------------------------------------------------
    // APB register logic
    // ------------------------------------------------------------

    always @(posedge pclk) begin

        if (!presetn) begin

            tx_register <= 32'b0;
            start_pulse <= 1'b0;

        end

        else begin

            // Default: no start pulse
            start_pulse <= 1'b0;

            if (apb_write) begin

                case (paddr[3:2])

                    // TX DATA
                    2'b00:
                        tx_register <= pwdata;

                    // CONTROL
                    2'b01:
                        if (pwdata[0])
                            start_pulse <= 1'b1;

                    default:
                        begin
                        end

                endcase

            end

        end

    end


    // ------------------------------------------------------------
    // SPI MASTER TOP
    // ------------------------------------------------------------

    spi_master_top spi_master (
        .clk     (pclk),
        .reset   (!presetn),

        .start   (start_pulse),
        .tx_data (tx_register[7:0]),
        .miso    (miso),

        .mosi    (mosi),
        .sclk    (sclk),
        .cs      (cs),

        .rx_data (rx_data),
        .busy    (busy),
        .done    (done)
    );

endmodule

Peripheral-Configuration-Distribution-Controller/tb/apb_peripheral_controller_tb.v
`timescale 1ns/1ps

module apb_peripheral_controller_tb;

    reg pclk;
    reg presetn;

    reg [7:0]  paddr;
    reg        psel;
    reg        penable;
    reg        pwrite;
    reg [31:0] pwdata;

    wire [31:0] prdata;
    wire        pready;
    wire        pslverr;

    reg         miso;
    wire        mosi;
    wire        sclk;
    wire        cs;
    wire        busy;
    wire        done;

    reg [7:0] slave_tx_data;
    reg [7:0] slave_rx_data;

    integer bit_count;
    integer errors;

    reg [31:0] read_data;

    // ============================================================
    // DUT
    // ============================================================

    apb_peripheral_controller dut (
        .pclk(pclk),
        .presetn(presetn),
        .paddr(paddr),
        .psel(psel),
        .penable(penable),
        .pwrite(pwrite),
        .pwdata(pwdata),
        .prdata(prdata),
        .pready(pready),
        .pslverr(pslverr),
        .miso(miso),
        .mosi(mosi),
        .sclk(sclk),
        .cs(cs),
        .busy(busy),
        .done(done)
    );

    // ============================================================
    // CLOCK
    // ============================================================

    always #5 pclk = ~pclk;

    // ============================================================
    // SPI SLAVE MODEL
    // LSB FIRST
    //
    // MISO is changed on falling edge.
    // MOSI is sampled slightly after rising edge to avoid
    // simulator race conditions.
    // ============================================================

    always @(negedge sclk) begin
        if (!cs) begin
            #1;
            miso <= slave_tx_data[bit_count];
        end
    end

    always @(posedge sclk) begin
        if (!cs) begin
            #1;

            slave_rx_data[bit_count] = mosi;

            if (bit_count < 7)
                bit_count = bit_count + 1;
            else
                bit_count = 0;
        end
    end

    // ============================================================
    // APB WRITE
    // ============================================================

    task apb_write;
        input [7:0]  addr;
        input [31:0] data;

        begin
            // SETUP
            @(posedge pclk);

            paddr   <= addr;
            pwdata  <= data;
            pwrite  <= 1'b1;
            psel    <= 1'b1;
            penable <= 1'b0;

            // ACCESS
            @(posedge pclk);

            penable <= 1'b1;

            // COMPLETE
            @(posedge pclk);

            psel    <= 1'b0;
            penable <= 1'b0;
            pwrite  <= 1'b0;
            paddr   <= 8'b0;
            pwdata  <= 32'b0;
        end
    endtask

    // ============================================================
    // APB READ
    // ============================================================

    task apb_read;
        input  [7:0] addr;
        output [31:0] data;

        begin
            // SETUP
            @(posedge pclk);

            paddr   <= addr;
            pwrite  <= 1'b0;
            psel    <= 1'b1;
            penable <= 1'b0;

            // ACCESS
            @(posedge pclk);

            penable <= 1'b1;

            #1;
            data = prdata;

            // COMPLETE
            @(posedge pclk);

            psel    <= 1'b0;
            penable <= 1'b0;
            paddr   <= 8'b0;
        end
    endtask

    // ============================================================
    // TEST
    // ============================================================

    initial begin

        $dumpfile("sim/waves/apb_peripheral_controller.vcd");
        $dumpvars(0, apb_peripheral_controller_tb);

        // --------------------------------------------------------
        // INITIALIZE
        // --------------------------------------------------------

        pclk          = 1'b0;
        presetn       = 1'b0;

        paddr         = 8'b0;
        psel          = 1'b0;
        penable       = 1'b0;
        pwrite        = 1'b0;
        pwdata        = 32'b0;

        slave_tx_data = 8'h65;
        slave_rx_data = 8'h00;

        bit_count     = 0;
        errors        = 0;

        // First MISO bit must already be present.
        miso = slave_tx_data[0];

        // --------------------------------------------------------
        // RESET
        // --------------------------------------------------------

        #20;

        presetn = 1'b1;

        #10;

        // --------------------------------------------------------
        // PREADY
        // --------------------------------------------------------

        if (pready === 1'b1)
            $display("PASS: PREADY");
        else begin
            $display("ERROR: PREADY");
            errors = errors + 1;
        end

        // --------------------------------------------------------
        // PSLVERR
        // --------------------------------------------------------

        if (pslverr === 1'b0)
            $display("PASS: PSLVERR");
        else begin
            $display("ERROR: PSLVERR");
            errors = errors + 1;
        end

        // --------------------------------------------------------
        // WRITE TX REGISTER
        // Address = 0x00
        // Data = A5
        // --------------------------------------------------------

        apb_write(8'h00, 32'h000000A5);

        // --------------------------------------------------------
        // READ TX REGISTER
        // --------------------------------------------------------

        apb_read(8'h00, read_data);

        if (read_data === 32'h000000A5)
            $display("PASS: TX register readback");
        else begin
            $display(
                "ERROR: TX register readback | Expected=A5 | Got=%h",
                read_data
            );
            errors = errors + 1;
        end

        // --------------------------------------------------------
        // RESET SPI SLAVE STATE
        // --------------------------------------------------------

        slave_rx_data = 8'h00;
        bit_count     = 0;

        // First received MISO bit
        miso = slave_tx_data[0];

        // --------------------------------------------------------
        // START SPI
        // Address = 0x04
        // --------------------------------------------------------

        apb_write(8'h04, 32'h00000001);

        // Allow start pulse to propagate
        @(posedge pclk);
        #1;

        if (busy === 1'b1)
            $display("PASS: SPI transaction started through APB");
        else begin
            $display("ERROR: SPI transaction did not start through APB");
            errors = errors + 1;
        end

        // --------------------------------------------------------
        // WAIT FOR SPI COMPLETE
        // --------------------------------------------------------

        wait(done === 1'b1);

        #2;

        // --------------------------------------------------------
        // CHECK SPI TX
        // --------------------------------------------------------

        if (slave_rx_data === 8'hA5)
            $display("PASS: SPI TX through APB");
        else begin
            $display(
                "ERROR: SPI TX | Expected=A5 | Got=%h",
                slave_rx_data
            );
            errors = errors + 1;
        end

        // --------------------------------------------------------
        // READ SPI RX REGISTER
        // Address = 0x08
        // --------------------------------------------------------

        apb_read(8'h08, read_data);

        if (read_data[7:0] === 8'h65)
            $display("PASS: SPI RX through APB");
        else begin
            $display(
                "ERROR: SPI RX | Expected=65 | Got=%h",
                read_data[7:0]
            );
            errors = errors + 1;
        end

        // --------------------------------------------------------
        // FINAL RESULT
        // --------------------------------------------------------

        if (errors == 0) begin
            $display("--------------------------------");
            $display("APB PERIPHERAL CONTROLLER TEST PASSED");
            $display("--------------------------------");
        end
        else begin
            $display("--------------------------------");
            $display(
                "APB PERIPHERAL CONTROLLER TEST FAILED: %0d errors",
                errors
            );
            $display("--------------------------------");
        end

        #20;
        $finish;

    end

endmodule

Peripheral-Configuration-Distribution-Controller/sim/waves/apb_peripheral_controller.vcd
$date
	Fri Oct  2 00:52:19 2026
$end
$version
	Icarus Verilog
$end
$timescale
	1ps
$end
$scope module apb_peripheral_controller_tb $end
$var wire 1 ! pready $end
$var wire 1 " pslverr $end
$var wire 1 # sclk $end
$var wire 32 $ prdata [31:0] $end
$var wire 1 % mosi $end
$var wire 1 & done $end
$var wire 1 ' cs $end
$var wire 1 ( busy $end
$var reg 1 ) miso $end
$var reg 8 * paddr [7:0] $end
$var reg 1 + pclk $end
$var reg 1 , penable $end
$var reg 1 - presetn $end
$var reg 1 . psel $end
$var reg 32 / pwdata [31:0] $end
$var reg 1 0 pwrite $end
$var reg 32 1 read_data [31:0] $end
$var reg 8 2 slave_rx_data [7:0] $end
$var reg 8 3 slave_tx_data [7:0] $end
$var integer 32 4 bit_count [31:0] $end
$var integer 32 5 errors [31:0] $end
$scope module dut $end
$var wire 1 6 apb_write $end
$var wire 1 ) miso $end
$var wire 8 7 paddr [7:0] $end
$var wire 1 + pclk $end
$var wire 1 , penable $end
$var wire 1 ! pready $end
$var wire 1 - presetn $end
$var wire 1 . psel $end
$var wire 1 " pslverr $end
$var wire 32 8 pwdata [31:0] $end
$var wire 1 0 pwrite $end
$var wire 1 # sclk $end
$var wire 8 9 rx_data [7:0] $end
$var wire 32 : prdata [31:0] $end
$var wire 1 % mosi $end
$var wire 1 & done $end
$var wire 1 ' cs $end
$var wire 1 ( busy $end
$var reg 1 ; start_pulse $end
$var reg 32 < tx_register [31:0] $end
$scope module spi_master $end
$var wire 1 ( busy $end
$var wire 1 + clk $end
$var wire 1 ' cs $end
$var wire 1 ) miso $end
$var wire 1 % mosi $end
$var wire 1 = reset $end
$var wire 8 > rx_data [7:0] $end
$var wire 1 ; start $end
$var wire 8 ? tx_data [7:0] $end
$var wire 1 @ spi_clk $end
$var wire 1 A sipo_valid $end
$var wire 8 B sipo_parallel [7:0] $end
$var wire 1 C piso_valid $end
$var wire 1 D piso_serial $end
$var wire 1 & done $end
$var reg 1 E active $end
$var reg 3 F bit_count [2:0] $end
$var reg 1 & done_reg $end
$var reg 1 G first_sample_done $end
$var reg 1 H piso_enable $end
$var reg 1 I piso_load $end
$var reg 1 # sclk $end
$var reg 1 J sipo_enable $end
$var reg 1 K spi_clk_prev $end
$scope module clk_div $end
$var wire 1 + clk $end
$var wire 1 = reset $end
$var reg 1 @ clk_out $end
$var reg 2 L count [1:0] $end
$upscope $end
$scope module rx_sipo $end
$var wire 1 + clk $end
$var wire 1 J enable $end
$var wire 1 = reset $end
$var wire 1 ) serial_in $end
$var reg 3 M bit_count [2:0] $end
$var reg 8 N parallel_out [7:0] $end
$var reg 8 O shift_reg [7:0] $end
$var reg 1 A valid $end
$upscope $end
$scope module tx_piso $end
$var wire 1 + clk $end
$var wire 1 H enable $end
$var wire 1 I load $end
$var wire 8 P parallel_in [7:0] $end
$var wire 1 = reset $end
$var reg 3 Q bit_count [2:0] $end
$var reg 1 D serial_out $end
$var reg 8 R shift_reg [7:0] $end
$var reg 1 C valid $end
$upscope $end
$upscope $end
$upscope $end
$scope task apb_read $end
$var reg 8 S addr [7:0] $end
$var reg 32 T data [31:0] $end
$upscope $end
$scope task apb_write $end
$var reg 8 U addr [7:0] $end
$var reg 32 V data [31:0] $end
$upscope $end
$upscope $end
$enddefinitions $end
$comment Show the parameter values. $end
$dumpall
$end
#0
$dumpvars
bx V
bx U
bx T
bx S
bx R
bx Q
bx P
bx O
bx N
bx M
bx L
xK
xJ
xI
xH
xG
bx F
xE
xD
xC
bx B
xA
x@
bx ?
bx >
1=
bx <
x;
bx :
bx 9
b0 8
b0 7
06
b0 5
b0 4
b1100101 3
b0 2
bx 1
00
b0 /
0.
0-
0,
0+
b0 *
1)
x(
x'
x&
x%
bx $
x#
0"
1!
$end
#5000
1'
b0 $
b0 :
b0 ?
b0 P
0@
b0 L
0C
0%
0D
b0 Q
b0 R
0A
b0 M
b0 9
b0 >
b0 B
b0 N
b0 O
0#
0G
0K
0&
0(
0E
b0 F
0J
0H
0I
0;
b0 <
1+
#10000
0+
#15000
1+
#20000
0+
0=
1-
#25000
b1 L
1+
#30000
0+
b10100101 V
b0 U
#35000
1@
b0 L
1.
10
b10100101 /
b10100101 8
1+
#40000
0+
#45000
16
1,
b1 L
1+
#50000
0+
#55000
b10100101 $
b10100101 :
b10100101 ?
b10100101 P
06
b10100101 <
0@
b0 L
b0 /
b0 8
00
0,
0.
b0 S
1+
#60000
0+
#65000
b1 L
1.
1+
#70000
0+
#75000
1,
1@
b0 L
1+
#76000
b10100101 T
#80000
0+
#85000
b1 L
0,
0.
b1 V
b100 U
b10100101 1
1+
#90000
0+
#95000
b0 $
b0 :
0@
b0 L
1.
10
b1 /
b1 8
b100 *
b100 7
1+
#100000
0+
#105000
16
1,
b1 L
1+
#110000
0+
#115000
b10100101 $
b10100101 :
06
1;
1@
b0 L
b0 /
b0 8
b0 *
b0 7
00
0,
0.
1+
#120000
0+
#125000
0'
b1 L
1K
1(
1E
1I
0;
1+
#130000
0+
#135000
0I
1%
1D
b10100101 R
0@
b0 L
1+
#140000
0+
#145000
b1 L
0K
1+
#150000
0+
#155000
1@
b0 L
1+
#160000
0+
#165000
b1 L
1K
1G
1#
1J
1+
#166000
b1 4
b1 2
#170000
0+
#175000
0J
b1 M
b10000000 O
0@
b0 L
1+
#180000
0+
#185000
b1 L
0K
b1 F
1H
0#
1+
#186000
0)
#190000
0+
#195000
0H
0%
0D
b1 Q
b1010010 R
1@
b0 L
1+
#200000
0+
#205000
b1 L
1K
1#
1J
1+
#206000
b10 4
#210000
0+
#215000
0J
b10 M
b1000000 O
0@
b0 L
1+
#220000
0+
#225000
b1 L
0K
b10 F
1H
0#
1+
#226000
1)
#230000
0+
#235000
0H
1%
1D
b10 Q
b101001 R
1@
b0 L
1+
#240000
0+
#245000
b1 L
1K
1#
1J
1+
#246000
b11 4
b101 2
#250000
0+
#255000
0J
b11 M
b10100000 O
0@
b0 L
1+
#260000
0+
#265000
b1 L
0K
b11 F
1H
0#
1+
#266000
0)
#270000
0+
#275000
0H
0%
0D
b11 Q
b10100 R
1@
b0 L
1+
#280000
0+
#285000
b1 L
1K
1#
1J
1+
#286000
b100 4
#290000
0+
#295000
0J
b100 M
b1010000 O
0@
b0 L
1+
#300000
0+
#305000
b1 L
0K
b100 F
1H
0#
1+
#310000
0+
#315000
0H
b100 Q
b1010 R
1@
b0 L
1+
#320000
0+
#325000
b1 L
1K
1#
1J
1+
#326000
b101 4
#330000
0+
#335000
0J
b101 M
b101000 O
0@
b0 L
1+
#340000
0+
#345000
b1 L
0K
b101 F
1H
0#
1+
#346000
1)
#350000
0+
#355000
0H
1%
1D
b101 Q
b101 R
1@
b0 L
1+
#360000
0+
#365000
b1 L
1K
1#
1J
1+
#366000
b110 4
b100101 2
#370000
0+
#375000
0J
b110 M
b10010100 O
0@
b0 L
1+
#380000
0+
#385000
b1 L
0K
b110 F
1H
0#
1+
#390000
0+
#395000
0H
0%
0D
b110 Q
b10 R
1@
b0 L
1+
#400000
0+
#405000
b1 L
1K
1#
1J
1+
#406000
b111 4
#410000
0+
#415000
0J
b111 M
b11001010 O
0@
b0 L
1+
#420000
0+
#425000
b1 L
0K
b111 F
1H
0#
1+
#426000
0)
#430000
0+
#435000
0H
1%
1D
b111 Q
b1 R
1@
b0 L
1+
#440000
0+
#445000
b1 L
1K
1#
1J
1+
#446000
b0 4
b10100101 2
#450000
0+
#455000
0J
1A
b0 M
b1100101 9
b1100101 >
b1100101 B
b1100101 N
b1100101 O
0@
b0 L
1+
#460000
0+
#465000
1'
b1 L
0A
0K
1&
0(
0E
0#
1+
#466000
1)
#467000
b1000 S
#470000
0+
#475000
b1100101 $
b1100101 :
0&
1@
b0 L
1.
b1000 *
b1000 7
1+
#480000
0+
#485000
1,
b1 L
1+
#486000
b1100101 T
#490000
0+
#495000
b10100101 $
b10100101 :
0@
b0 L
b0 *
b0 7
0,
0.
b1100101 1
1+
#500000
0+
#505000
b1 L
1+
#510000
0+
#515000
1@
b0 L
1+
