Peripheral-Configuration-Distribution-Controller/rtl/peripheral_controller.v
module peripheral_controller (
    input  wire       clk,
    input  wire       reset,

    input  wire       start,
    input  wire [7:0] tx_data,
    input  wire       miso,

    output reg        mosi,
    output reg        sclk,
    output reg        cs,

    output reg [7:0]  rx_data,
    output reg        busy,
    output reg        done
);

    // --------------------------------------------------
    // Internal registers
    // --------------------------------------------------

    reg [7:0] tx_shift;
    reg [7:0] rx_shift;

    reg [3:0] bit_count;

    reg [1:0] clk_count;

    // --------------------------------------------------
    // SPI clock generation
    //
    // CPU clock is divided to generate SPI clock.
    // --------------------------------------------------

    always @(posedge clk) begin

        if (reset) begin

            tx_shift <= 8'b0;
            rx_shift <= 8'b0;

            bit_count <= 4'd0;
            clk_count <= 2'd0;

            mosi <= 1'b0;
            sclk <= 1'b0;
            cs   <= 1'b1;

            rx_data <= 8'b0;

            busy <= 1'b0;
            done <= 1'b0;

        end

        else begin

            done <= 1'b0;

            // --------------------------------------------------
            // Start a new SPI transaction
            // --------------------------------------------------

            if (start && !busy) begin

                tx_shift <= tx_data;
                rx_shift <= 8'b0;

                bit_count <= 4'd0;
                clk_count <= 2'd0;

                // First bit is placed on MOSI before
                // the first SPI clock edge.
                mosi <= tx_data[7];

                sclk <= 1'b0;
                cs   <= 1'b0;

                busy <= 1'b1;

            end

            // --------------------------------------------------
            // SPI transaction
            // --------------------------------------------------

            else if (busy) begin

                if (clk_count == 2'd1) begin

                    clk_count <= 2'd0;

                    // ------------------------------------------
                    // Rising SPI edge
                    // Sample MISO
                    // ------------------------------------------

                    if (sclk == 1'b0) begin

                        sclk <= 1'b1;

                        rx_shift <= {
                            rx_shift[6:0],
                            miso
                        };

                    end

                    // ------------------------------------------
                    // Falling SPI edge
                    // Shift TX data
                    // ------------------------------------------

                    else begin

                        sclk <= 1'b0;

                        if (bit_count == 4'd7) begin

                            // Transaction complete

                            rx_data <= rx_shift;

                            mosi <= 1'b0;

                            cs <= 1'b1;

                            busy <= 1'b0;

                            done <= 1'b1;

                        end

                        else begin

                            bit_count <= bit_count + 1'b1;

                            tx_shift <= {
                                tx_shift[6:0],
                                1'b0
                            };

                            mosi <= tx_shift[6];

                        end

                    end

                end

                else begin

                    clk_count <= clk_count + 1'b1;

                end

            end

        end

    end

endmodule

Peripheral-Configuration-Distribution-Controller/rtl/apb_peripheral_controller.v
module apb_peripheral_controller (
    input  wire        pclk,
    input  wire        presetn,

    input  wire [7:0]  paddr,
    input  wire        psel,
    input  wire        penable,
    input  wire        pwrite,
    input  wire [31:0] pwdata,

    output wire [31:0] prdata,
    output wire        pready,
    output wire        pslverr,

    input  wire        miso,

    output wire        mosi,
    output wire        sclk,
    output wire        cs,

    output wire        busy,
    output wire        done
);

    reg [31:0] tx_register;
    reg        start_pulse;

    wire [7:0] rx_data;

    wire apb_write;

    assign apb_write = psel && penable && pwrite;

    assign pready  = 1'b1;
    assign pslverr = 1'b0;

    assign prdata =
        (paddr[3:2] == 2'b00) ? tx_register :
        (paddr[3:2] == 2'b01) ? {31'b0, busy} :
        (paddr[3:2] == 2'b10) ? {24'b0, rx_data} :
        (paddr[3:2] == 2'b11) ? {30'b0, done, busy} :
        32'b0;

    always @(posedge pclk) begin

        if (!presetn) begin
            tx_register <= 32'b0;
            start_pulse <= 1'b0;
        end

        else begin

            start_pulse <= 1'b0;

            if (apb_write) begin

                case (paddr[3:2])

                    2'b00: begin
                        tx_register <= pwdata;
                    end

                    2'b01: begin
                        if (pwdata[0])
                            start_pulse <= 1'b1;
                    end

                    default: begin
                    end

                endcase

            end

        end

    end

    peripheral_controller spi_controller (
        .clk     (pclk),
        .reset   (!presetn),

        .start   (start_pulse),
        .tx_data (tx_register[7:0]),
        .miso    (miso),

        .mosi    (mosi),
        .sclk    (sclk),
        .cs      (cs),

        .rx_data (rx_data),
        .busy    (busy),
        .done    (done)
    );

endmodule

Peripheral-Configuration-Distribution-Controller/rtl/axi_apb_peripheral_controller.v
module axi_apb_peripheral_controller (
    input  wire        aclk,
    input  wire        aresetn,

    input  wire [7:0]  awaddr,
    input  wire        awvalid,
    output wire        awready,

    input  wire [31:0] wdata,
    input  wire [3:0]  wstrb,
    input  wire        wvalid,
    output wire        wready,

    output reg  [1:0]  bresp,
    output reg         bvalid,
    input  wire        bready,

    input  wire [7:0]  araddr,
    input  wire        arvalid,
    output wire        arready,

    output reg  [31:0] rdata,
    output reg  [1:0]  rresp,
    output reg         rvalid,
    input  wire        rready,

    input  wire        miso,

    output wire        mosi,
    output wire        sclk,
    output wire        cs
);

    localparam IDLE       = 3'd0;
    localparam W_SETUP    = 3'd1;
    localparam W_ACCESS   = 3'd2;
    localparam B_RESPONSE = 3'd3;
    localparam R_SETUP    = 3'd4;
    localparam R_ACCESS   = 3'd5;
    localparam R_RESPONSE = 3'd6;

    reg [2:0] state;

    reg [7:0]  apb_addr;
    reg [31:0] apb_wdata;
    reg        apb_pwrite;

    wire        apb_psel;
    wire        apb_penable;
    wire [31:0] apb_rdata;
    wire        apb_pready;
    wire        apb_pslverr;

    wire busy;
    wire done;

    // ----------------------------------------------------
    // AXI READY
    // ----------------------------------------------------

    assign awready = (state == IDLE);
    assign wready  = (state == IDLE);
    assign arready = (state == IDLE);

    // ----------------------------------------------------
    // APB CONTROL
    // ----------------------------------------------------

    assign apb_psel =
        (state == W_SETUP)  ||
        (state == W_ACCESS) ||
        (state == R_SETUP)  ||
        (state == R_ACCESS);

    assign apb_penable =
        (state == W_ACCESS) ||
        (state == R_ACCESS);

    // ----------------------------------------------------
    // AXI / APB FSM
    // ----------------------------------------------------

    always @(posedge aclk) begin

        if (!aresetn) begin

            state <= IDLE;

            apb_addr   <= 8'b0;
            apb_wdata  <= 32'b0;
            apb_pwrite <= 1'b0;

            bvalid <= 1'b0;
            bresp  <= 2'b00;

            rvalid <= 1'b0;
            rdata  <= 32'b0;
            rresp  <= 2'b00;

        end else begin

            case (state)

                // ----------------------------------------
                // IDLE
                // ----------------------------------------

                IDLE: begin

                    if (awvalid && wvalid) begin

                        apb_addr   <= awaddr;
                        apb_wdata  <= wdata;
                        apb_pwrite <= 1'b1;

                        state <= W_SETUP;

                    end else if (arvalid) begin

                        apb_addr   <= araddr;
                        apb_wdata  <= 32'b0;
                        apb_pwrite <= 1'b0;

                        state <= R_SETUP;

                    end

                end

                // ----------------------------------------
                // APB WRITE SETUP
                // ----------------------------------------

                W_SETUP: begin
                    state <= W_ACCESS;
                end

                // ----------------------------------------
                // APB WRITE ACCESS
                // ----------------------------------------

                W_ACCESS: begin

                    if (apb_pready) begin

                        bresp  <= apb_pslverr ? 2'b10 : 2'b00;
                        bvalid <= 1'b1;

                        state <= B_RESPONSE;

                    end

                end

                // ----------------------------------------
                // AXI WRITE RESPONSE
                // ----------------------------------------

                B_RESPONSE: begin

                    if (bready) begin

                        bvalid <= 1'b0;

                        state <= IDLE;

                    end

                end

                // ----------------------------------------
                // APB READ SETUP
                // ----------------------------------------

                R_SETUP: begin
                    state <= R_ACCESS;
                end

                // ----------------------------------------
                // APB READ ACCESS
                // ----------------------------------------

                R_ACCESS: begin

                    if (apb_pready) begin

                        rdata <= apb_rdata;
                        rresp <= apb_pslverr ? 2'b10 : 2'b00;

                        rvalid <= 1'b1;

                        state <= R_RESPONSE;

                    end

                end

                // ----------------------------------------
                // AXI READ RESPONSE
                // ----------------------------------------

                R_RESPONSE: begin

                    if (rready) begin

                        rvalid <= 1'b0;

                        state <= IDLE;

                    end

                end

                default: begin
                    state <= IDLE;
                end

            endcase

        end

    end

    // ----------------------------------------------------
    // APB PERIPHERAL CONTROLLER
    // ----------------------------------------------------

    apb_peripheral_controller apb_spi (

        .pclk    (aclk),
        .presetn (aresetn),

        .paddr   (apb_addr),
        .psel    (apb_psel),
        .penable (apb_penable),
        .pwrite  (apb_pwrite),
        .pwdata  (apb_wdata),

        .prdata  (apb_rdata),
        .pready  (apb_pready),
        .pslverr (apb_pslverr),

        .miso    (miso),

        .mosi    (mosi),
        .sclk    (sclk),
        .cs      (cs),

        .busy    (busy),
        .done    (done)
    );

endmodule

Peripheral-Configuration-Distribution-Controller/tb/axi_apb_peripheral_controller_tb.v
`timescale 1ns/1ps

module axi_apb_peripheral_controller_tb;

    reg aclk;
    reg aresetn;

    reg [7:0]  awaddr;
    reg        awvalid;
    wire       awready;

    reg [31:0] wdata;
    reg [3:0]  wstrb;
    reg        wvalid;
    wire       wready;

    wire [1:0] bresp;
    wire       bvalid;
    reg        bready;

    reg [7:0]  araddr;
    reg        arvalid;
    wire       arready;

    wire [31:0] rdata;
    wire [1:0]  rresp;
    wire        rvalid;
    reg        rready;

    reg        miso;

    wire       mosi;
    wire       sclk;
    wire       cs;

    reg [7:0] slave_tx_data;
    reg [7:0] slave_rx_data;

    integer bit_count;
    integer errors;

    axi_apb_peripheral_controller dut (
        .aclk    (aclk),
        .aresetn (aresetn),

        .awaddr  (awaddr),
        .awvalid (awvalid),
        .awready (awready),

        .wdata   (wdata),
        .wstrb   (wstrb),
        .wvalid  (wvalid),
        .wready  (wready),

        .bresp   (bresp),
        .bvalid  (bvalid),
        .bready  (bready),

        .araddr  (araddr),
        .arvalid (arvalid),
        .arready (arready),

        .rdata   (rdata),
        .rresp   (rresp),
        .rvalid  (rvalid),
        .rready  (rready),

        .miso    (miso),

        .mosi    (mosi),
        .sclk    (sclk),
        .cs      (cs)
    );

    always #5 aclk = ~aclk;

    always @(negedge sclk) begin
        if (!cs)
            miso <= slave_tx_data[7-bit_count];
    end

    always @(posedge sclk) begin

        if (!cs) begin

            slave_rx_data[7-bit_count] = mosi;

            if (bit_count < 7)
                bit_count = bit_count + 1;
            else
                bit_count = 0;

        end

    end

    task axi_write;
        input [7:0] addr;
        input [31:0] data;

        begin

            @(posedge aclk);

            awaddr  <= addr;
            awvalid <= 1'b1;

            wdata   <= data;
            wstrb   <= 4'b1111;
            wvalid  <= 1'b1;

            wait(awready && wready);

            @(posedge aclk);

            awvalid <= 1'b0;
            wvalid  <= 1'b0;

            wait(bvalid);

            if (bresp !== 2'b00) begin
                $display("ERROR: AXI write response");
                errors = errors + 1;
            end
            else begin
                $display("PASS: AXI write response");
            end

            bready <= 1'b1;

            @(posedge aclk);

            bready <= 1'b0;

        end
    endtask

    task axi_read;
        input [7:0] addr;

        begin

            @(posedge aclk);

            araddr  <= addr;
            arvalid <= 1'b1;

            wait(arready);

            @(posedge aclk);

            arvalid <= 1'b0;

            wait(rvalid);

            if (rresp !== 2'b00) begin
                $display("ERROR: AXI read response");
                errors = errors + 1;
            end
            else begin
                $display("PASS: AXI read response");
            end

            rready <= 1'b1;

            @(posedge aclk);

            rready <= 1'b0;

        end
    endtask

    initial begin

        $dumpfile("sim/waves/axi_apb_peripheral_controller.vcd");
        $dumpvars(0, axi_apb_peripheral_controller_tb);

        aclk    = 1'b0;
        aresetn = 1'b0;

        awaddr  = 8'b0;
        awvalid = 1'b0;

        wdata   = 32'b0;
        wstrb   = 4'b1111;
        wvalid  = 1'b0;

        bready  = 1'b0;

        araddr  = 8'b0;
        arvalid = 1'b0;

        rready  = 1'b0;

        miso = 1'b0;

        slave_tx_data = 8'h65;
        slave_rx_data = 8'b0;

        bit_count = 0;
        errors = 0;

        #20;

        aresetn = 1'b1;

        // -----------------------------------------------
        // Write TX register through AXI
        // -----------------------------------------------

        axi_write(8'h00, 32'h000000A5);

        $display("PASS: TX register written through AXI");

        // -----------------------------------------------
        // Read TX register through AXI
        // -----------------------------------------------

        axi_read(8'h00);

        if (rdata !== 32'h000000A5) begin

            $display(
                "ERROR: TX readback | Expected=%h | Got=%h",
                32'h000000A5,
                rdata
            );

            errors = errors + 1;

        end
        else begin
            $display("PASS: TX register read through AXI");
        end

        // -----------------------------------------------
        // Start SPI through AXI
        // -----------------------------------------------

        axi_write(8'h04, 32'h00000001);

        wait(cs == 1'b0);

        $display("PASS: SPI transaction started through AXI");

        wait(cs == 1'b1);

        // -----------------------------------------------
        // Verify SPI TX
        // -----------------------------------------------

        if (slave_rx_data !== 8'hA5) begin

            $display(
                "ERROR: SPI TX | Expected=%h | Got=%h",
                8'hA5,
                slave_rx_data
            );

            errors = errors + 1;

        end
        else begin
            $display("PASS: SPI TX through AXI -> APB");
        end

        // -----------------------------------------------
        // Read RX register through AXI
        // -----------------------------------------------

        axi_read(8'h08);

        if (rdata[7:0] !== slave_tx_data) begin

            $display(
                "ERROR: SPI RX | Expected=%h | Got=%h",
                slave_tx_data,
                rdata[7:0]
            );

            errors = errors + 1;

        end
        else begin
            $display("PASS: SPI RX through AXI -> APB");
        end

        // -----------------------------------------------
        // Final
        // -----------------------------------------------

        if (errors == 0) begin

            $display("--------------------------------");
            $display("AXI APB PERIPHERAL CONTROLLER TEST PASSED");
            $display("--------------------------------");

        end
        else begin

            $display("--------------------------------");
            $display(
                "AXI APB PERIPHERAL CONTROLLER TEST FAILED: %0d errors",
                errors
            );
            $display("--------------------------------");

        end

        $finish;

    end

endmodule

Peripheral-Configuration-Distribution-Controller/sim/waves/axi_apb_peripheral_controller.vcd
$date
	Tue Sep 29 13:57:41 2026
$end
$version
	Icarus Verilog
$end
$timescale
	1ps
$end
$scope module axi_apb_peripheral_controller_tb $end
$var wire 1 ! wready $end
$var wire 1 " sclk $end
$var wire 1 # rvalid $end
$var wire 2 $ rresp [1:0] $end
$var wire 32 % rdata [31:0] $end
$var wire 1 & mosi $end
$var wire 1 ' cs $end
$var wire 1 ( bvalid $end
$var wire 2 ) bresp [1:0] $end
$var wire 1 * awready $end
$var wire 1 + arready $end
$var reg 1 , aclk $end
$var reg 8 - araddr [7:0] $end
$var reg 1 . aresetn $end
$var reg 1 / arvalid $end
$var reg 8 0 awaddr [7:0] $end
$var reg 1 1 awvalid $end
$var reg 1 2 bready $end
$var reg 1 3 miso $end
$var reg 1 4 rready $end
$var reg 8 5 slave_rx_data [7:0] $end
$var reg 8 6 slave_tx_data [7:0] $end
$var reg 32 7 wdata [31:0] $end
$var reg 4 8 wstrb [3:0] $end
$var reg 1 9 wvalid $end
$var integer 32 : bit_count [31:0] $end
$var integer 32 ; errors [31:0] $end
$scope module dut $end
$var wire 1 , aclk $end
$var wire 1 < apb_penable $end
$var wire 1 = apb_pready $end
$var wire 1 > apb_psel $end
$var wire 1 ? apb_pslverr $end
$var wire 8 @ araddr [7:0] $end
$var wire 1 . aresetn $end
$var wire 1 / arvalid $end
$var wire 8 A awaddr [7:0] $end
$var wire 1 1 awvalid $end
$var wire 1 2 bready $end
$var wire 1 3 miso $end
$var wire 1 4 rready $end
$var wire 32 B wdata [31:0] $end
$var wire 4 C wstrb [3:0] $end
$var wire 1 9 wvalid $end
$var wire 1 ! wready $end
$var wire 1 " sclk $end
$var wire 1 & mosi $end
$var wire 1 D done $end
$var wire 1 ' cs $end
$var wire 1 E busy $end
$var wire 1 * awready $end
$var wire 1 + arready $end
$var wire 32 F apb_rdata [31:0] $end
$var parameter 3 G B_RESPONSE $end
$var parameter 3 H IDLE $end
$var parameter 3 I R_ACCESS $end
$var parameter 3 J R_RESPONSE $end
$var parameter 3 K R_SETUP $end
$var parameter 3 L W_ACCESS $end
$var parameter 3 M W_SETUP $end
$var reg 8 N apb_addr [7:0] $end
$var reg 1 O apb_pwrite $end
$var reg 32 P apb_wdata [31:0] $end
$var reg 2 Q bresp [1:0] $end
$var reg 1 ( bvalid $end
$var reg 32 R rdata [31:0] $end
$var reg 2 S rresp [1:0] $end
$var reg 1 # rvalid $end
$var reg 3 T state [2:0] $end
$scope module apb_spi $end
$var wire 1 U apb_write $end
$var wire 1 3 miso $end
$var wire 8 V paddr [7:0] $end
$var wire 1 , pclk $end
$var wire 1 < penable $end
$var wire 1 = pready $end
$var wire 1 . presetn $end
$var wire 1 > psel $end
$var wire 1 ? pslverr $end
$var wire 32 W pwdata [31:0] $end
$var wire 1 O pwrite $end
$var wire 1 " sclk $end
$var wire 8 X rx_data [7:0] $end
$var wire 32 Y prdata [31:0] $end
$var wire 1 & mosi $end
$var wire 1 D done $end
$var wire 1 ' cs $end
$var wire 1 E busy $end
$var reg 1 Z start_pulse $end
$var reg 32 [ tx_register [31:0] $end
$scope module spi_controller $end
$var wire 1 , clk $end
$var wire 1 3 miso $end
$var wire 1 \ reset $end
$var wire 1 Z start $end
$var wire 8 ] tx_data [7:0] $end
$var reg 4 ^ bit_count [3:0] $end
$var reg 1 E busy $end
$var reg 2 _ clk_count [1:0] $end
$var reg 1 ' cs $end
$var reg 1 D done $end
$var reg 1 & mosi $end
$var reg 8 ` rx_data [7:0] $end
$var reg 8 a rx_shift [7:0] $end
$var reg 1 " sclk $end
$var reg 8 b tx_shift [7:0] $end
$upscope $end
$upscope $end
$upscope $end
$scope task axi_read $end
$var reg 8 c addr [7:0] $end
$upscope $end
$scope task axi_write $end
$var reg 8 d addr [7:0] $end
$var reg 32 e data [31:0] $end
$upscope $end
$upscope $end
$enddefinitions $end
$comment Show the parameter values. $end
$dumpall
b1 M
b10 L
b100 K
b110 J
b101 I
b0 H
b11 G
$end
#0
$dumpvars
bx e
bx d
bx c
bx b
bx a
bx `
bx _
bx ^
bx ]
1\
bx [
xZ
bx Y
bx X
bx W
bx V
xU
bx T
bx S
bx R
bx Q
bx P
xO
bx N
bx F
xE
xD
b1111 C
b0 B
b0 A
b0 @
0?
x>
1=
x<
b0 ;
b0 :
09
b1111 8
b0 7
b1100101 6
b0 5
04
03
02
01
b0 0
0/
0.
b0 -
0,
x+
x*
bx )
x(
x'
x&
bx %
bx $
x#
x"
x!
$end
#5000
0>
b0 F
b0 Y
b0 ]
0U
0<
0D
0E
b0 X
b0 `
1'
0"
0&
b0 _
b0 ^
b0 a
b0 b
0Z
b0 [
b0 $
b0 S
b0 %
b0 R
0#
b0 )
b0 Q
0(
0O
b0 P
b0 W
b0 N
b0 V
1*
1!
1+
b0 T
1,
#10000
0,
#15000
1,
#20000
0,
b10100101 e
b0 d
0\
1.
#25000
19
b10100101 7
b10100101 B
11
1,
#30000
0,
#35000
1>
09
01
0*
0!
0+
b1 T
1O
b10100101 P
b10100101 W
1,
#40000
0,
#45000
1U
1<
b10 T
1,
#50000
0,
#55000
12
0>
0U
0<
b10100101 F
b10100101 Y
b10100101 ]
b11 T
1(
b10100101 [
1,
#60000
0,
#65000
1*
1!
1+
b0 T
0(
02
b0 c
1,
#70000
0,
#75000
1/
1,
#80000
0,
#85000
1>
0/
0*
0!
0+
b100 T
0O
b0 P
b0 W
1,
#90000
0,
#95000
1<
b101 T
1,
#100000
0,
#105000
14
0>
0<
b110 T
1#
b10100101 %
b10100101 R
1,
#110000
0,
#115000
1*
1!
1+
b0 T
0#
04
b1 e
b100 d
1,
#120000
0,
#125000
19
b1 7
b1 B
11
b100 0
b100 A
1,
#130000
0,
#135000
1>
b0 F
b0 Y
09
01
0*
0!
0+
b1 T
1O
b1 P
b1 W
b100 N
b100 V
1,
#140000
0,
#145000
1U
1<
b10 T
1,
#150000
0,
#155000
12
0>
0U
0<
b11 T
1(
1Z
1,
#160000
0,
#165000
b1 F
b1 Y
1E
0'
1&
b10100101 b
0Z
1*
1!
1+
b0 T
0(
02
1,
#170000
0,
#175000
b1 _
1,
#180000
0,
#185000
b1 :
b10000000 5
1"
b0 _
1,
#190000
0,
#195000
b1 _
1,
#200000
0,
#205000
13
0&
b1001010 b
b1 ^
0"
b0 _
1,
#210000
0,
#215000
b1 _
1,
#220000
0,
#225000
b10 :
b1 a
1"
b0 _
1,
#230000
0,
#235000
b1 _
1,
#240000
0,
#245000
1&
b10010100 b
b10 ^
0"
b0 _
1,
#250000
0,
#255000
b1 _
1,
#260000
0,
#265000
b11 :
b10100000 5
b11 a
1"
b0 _
1,
#270000
0,
#275000
b1 _
1,
#280000
0,
#285000
03
0&
b101000 b
b11 ^
0"
b0 _
1,
#290000
0,
#295000
b1 _
1,
#300000
0,
#305000
b100 :
b110 a
1"
b0 _
1,
#310000
0,
#315000
b1 _
1,
#320000
0,
#325000
b1010000 b
b100 ^
0"
b0 _
1,
#330000
0,
#335000
b1 _
1,
#340000
0,
#345000
b101 :
b1100 a
1"
b0 _
1,
#350000
0,
#355000
b1 _
1,
#360000
0,
#365000
13
1&
b10100000 b
b101 ^
0"
b0 _
1,
#370000
0,
#375000
b1 _
1,
#380000
0,
#385000
b110 :
b10100100 5
b11001 a
1"
b0 _
1,
#390000
0,
#395000
b1 _
1,
#400000
0,
#405000
03
0&
b1000000 b
b110 ^
0"
b0 _
1,
#410000
0,
#415000
b1 _
1,
#420000
0,
#425000
b111 :
b110010 a
1"
b0 _
1,
#430000
0,
#435000
b1 _
1,
#440000
0,
#445000
13
1&
b10000000 b
b111 ^
0"
b0 _
1,
#450000
0,
#455000
b1 _
1,
#460000
0,
#465000
b0 :
b10100101 5
b1100101 a
1"
b0 _
1,
#470000
0,
#475000
b1 _
1,
#480000
0,
#485000
b0 F
b0 Y
b1000 c
1D
0E
1'
0&
b1100101 X
b1100101 `
0"
b0 _
1,
#490000
0,
#495000
0D
1/
b1000 -
b1000 @
1,
#500000
0,
#505000
b1100101 F
b1100101 Y
1>
0/
0*
0!
0+
b100 T
0O
b0 P
b0 W
b1000 N
b1000 V
1,
#510000
0,
#515000
1<
b101 T
1,
#520000
0,
#525000
14
0>
0<
b110 T
1#
b1100101 %
b1100101 R
1,
#530000
0,
#535000
1*
1!
1+
b0 T
0#
04
1,
