Peripheral-Configuration-Distribution-Controller/rtl/axi_interface.v
module axi_interface #(
    parameter ADDR_WIDTH = 8,
    parameter DATA_WIDTH = 32
)(
    input  wire                  aclk,
    input  wire                  aresetn,

    input  wire [ADDR_WIDTH-1:0] awaddr,
    input  wire                  awvalid,
    output wire                  awready,

    input  wire [DATA_WIDTH-1:0] wdata,
    input  wire [3:0]            wstrb,
    input  wire                  wvalid,
    output wire                  wready,

    output reg  [1:0]            bresp,
    output reg                   bvalid,
    input  wire                   bready,

    input  wire [ADDR_WIDTH-1:0] araddr,
    input  wire                  arvalid,
    output wire                  arready,

    output reg  [DATA_WIDTH-1:0] rdata,
    output reg  [1:0]            rresp,
    output reg                   rvalid,
    input  wire                   rready
);

    reg [DATA_WIDTH-1:0] memory [0:3];

    assign awready = 1'b1;
    assign wready  = 1'b1;
    assign arready = 1'b1;

    always @(posedge aclk) begin

        if (!aresetn) begin

            bvalid <= 1'b0;
            bresp  <= 2'b00;

            rvalid <= 1'b0;
            rresp  <= 2'b00;
            rdata  <= {DATA_WIDTH{1'b0}};

        end

        else begin

            if (awvalid && wvalid) begin

                memory[awaddr[3:2]] <= wdata;

                bvalid <= 1'b1;
                bresp  <= 2'b00;

            end

            if (bvalid && bready)
                bvalid <= 1'b0;

            if (arvalid) begin

                rdata <= memory[araddr[3:2]];

                rvalid <= 1'b1;
                rresp  <= 2'b00;

            end

            if (rvalid && rready)
                rvalid <= 1'b0;

        end

    end

endmodule

Peripheral-Configuration-Distribution-Controller/tb/axi_interface_tb.v
`timescale 1ns/1ps

module axi_interface_tb;

    reg aclk;
    reg aresetn;

    reg  [7:0]  awaddr;
    reg         awvalid;
    wire        awready;

    reg  [31:0] wdata;
    reg  [3:0]  wstrb;
    reg         wvalid;
    wire        wready;

    wire [1:0]  bresp;
    wire        bvalid;
    reg         bready;

    reg  [7:0]  araddr;
    reg         arvalid;
    wire        arready;

    wire [31:0] rdata;
    wire [1:0]  rresp;
    wire        rvalid;
    reg         rready;

    integer errors;

    axi_interface uut (
        .aclk    (aclk),
        .aresetn (aresetn),

        .awaddr  (awaddr),
        .awvalid (awvalid),
        .awready (awready),

        .wdata   (wdata),
        .wstrb   (wstrb),
        .wvalid  (wvalid),
        .wready  (wready),

        .bresp   (bresp),
        .bvalid  (bvalid),
        .bready  (bready),

        .araddr  (araddr),
        .arvalid (arvalid),
        .arready (arready),

        .rdata   (rdata),
        .rresp   (rresp),
        .rvalid  (rvalid),
        .rready  (rready)
    );

    always #5 aclk = ~aclk;

    initial begin

        $dumpfile("sim/waves/axi_interface.vcd");
        $dumpvars(0, axi_interface_tb);

        aclk    = 1'b0;
        aresetn = 1'b0;

        awaddr  = 8'b0;
        awvalid = 1'b0;

        wdata   = 32'b0;
        wstrb   = 4'b1111;
        wvalid  = 1'b0;

        bready  = 1'b0;

        araddr  = 8'b0;
        arvalid = 1'b0;

        rready  = 1'b0;

        errors = 0;

        // ------------------------------------------------
        // RESET
        // ------------------------------------------------

        @(posedge aclk);
        #1;

        aresetn = 1'b1;

        // ------------------------------------------------
        // Check READY signals
        // ------------------------------------------------

        if (awready !== 1'b1) begin
            $display("ERROR: AWREADY should be HIGH");
            errors = errors + 1;
        end
        else begin
            $display("PASS: AWREADY is HIGH");
        end

        if (wready !== 1'b1) begin
            $display("ERROR: WREADY should be HIGH");
            errors = errors + 1;
        end
        else begin
            $display("PASS: WREADY is HIGH");
        end

        if (arready !== 1'b1) begin
            $display("ERROR: ARREADY should be HIGH");
            errors = errors + 1;
        end
        else begin
            $display("PASS: ARREADY is HIGH");
        end

        // ------------------------------------------------
        // AXI WRITE TRANSACTION
        // Address = 0x00
        // Data    = A5A51234
        // ------------------------------------------------

        awaddr  = 8'h00;
        awvalid = 1'b1;

        wdata   = 32'hA5A5_1234;
        wstrb   = 4'b1111;
        wvalid  = 1'b1;

        @(posedge aclk);
        #1;

        if (bvalid !== 1'b1) begin
            $display("ERROR: BVALID not asserted after write");
            errors = errors + 1;
        end
        else begin
            $display("PASS: AXI write response generated");
        end

        if (bresp !== 2'b00) begin
            $display("ERROR: BRESP should indicate OKAY");
            errors = errors + 1;
        end
        else begin
            $display("PASS: BRESP = OKAY");
        end

        awvalid = 1'b0;
        wvalid  = 1'b0;

        // Accept write response

        bready = 1'b1;

        @(posedge aclk);
        #1;

        bready = 1'b0;

        if (bvalid !== 1'b0) begin
            $display("ERROR: BVALID did not clear");
            errors = errors + 1;
        end
        else begin
            $display("PASS: Write response handshake completed");
        end

        // ------------------------------------------------
        // AXI READ TRANSACTION
        // Address = 0x00
        // ------------------------------------------------

        araddr  = 8'h00;
        arvalid = 1'b1;

        @(posedge aclk);
        #1;

        if (rvalid !== 1'b1) begin
            $display("ERROR: RVALID not asserted after read");
            errors = errors + 1;
        end
        else begin
            $display("PASS: AXI read response generated");
        end

        if (rdata !== 32'hA5A5_1234) begin
            $display(
                "ERROR: Read data mismatch | Expected=%h | Got=%h",
                32'hA5A5_1234,
                rdata
            );
            errors = errors + 1;
        end
        else begin
            $display("PASS: Correct data returned from AXI read");
        end

        if (rresp !== 2'b00) begin
            $display("ERROR: RRESP should indicate OKAY");
            errors = errors + 1;
        end
        else begin
            $display("PASS: RRESP = OKAY");
        end

        arvalid = 1'b0;

        // Accept read response

        rready = 1'b1;

        @(posedge aclk);
        #1;

        rready = 1'b0;

        if (rvalid !== 1'b0) begin
            $display("ERROR: RVALID did not clear");
            errors = errors + 1;
        end
        else begin
            $display("PASS: Read response handshake completed");
        end

        // ------------------------------------------------
        // Final result
        // ------------------------------------------------

        if (errors == 0) begin
            $display("--------------------------------");
            $display("AXI INTERFACE TEST PASSED");
            $display("--------------------------------");
        end
        else begin
            $display("--------------------------------");
            $display(
                "AXI INTERFACE TEST FAILED: %0d errors",
                errors
            );
            $display("--------------------------------");
        end

        $finish;

    end

endmodule

Peripheral-Configuration-Distribution-Controller/sim/waves/axi_interface.vcd
$date
	Fri Oct  2 01:06:20 2026
$end
$version
	Icarus Verilog
$end
$timescale
	1ps
$end
$scope module axi_interface_tb $end
$var wire 1 ! arready $end
$var wire 1 " awready $end
$var wire 1 # wready $end
$var wire 1 $ rvalid $end
$var wire 2 % rresp [1:0] $end
$var wire 32 & rdata [31:0] $end
$var wire 1 ' bvalid $end
$var wire 2 ( bresp [1:0] $end
$var reg 1 ) aclk $end
$var reg 8 * araddr [7:0] $end
$var reg 1 + aresetn $end
$var reg 1 , arvalid $end
$var reg 8 - awaddr [7:0] $end
$var reg 1 . awvalid $end
$var reg 1 / bready $end
$var reg 1 0 rready $end
$var reg 32 1 wdata [31:0] $end
$var reg 4 2 wstrb [3:0] $end
$var reg 1 3 wvalid $end
$var integer 32 4 errors [31:0] $end
$scope module uut $end
$var wire 1 ) aclk $end
$var wire 8 5 araddr [7:0] $end
$var wire 1 + aresetn $end
$var wire 1 ! arready $end
$var wire 1 , arvalid $end
$var wire 8 6 awaddr [7:0] $end
$var wire 1 " awready $end
$var wire 1 . awvalid $end
$var wire 1 / bready $end
$var wire 1 0 rready $end
$var wire 32 7 wdata [31:0] $end
$var wire 1 # wready $end
$var wire 4 8 wstrb [3:0] $end
$var wire 1 3 wvalid $end
$var parameter 32 9 ADDR_WIDTH $end
$var parameter 32 : DATA_WIDTH $end
$var reg 2 ; bresp [1:0] $end
$var reg 1 ' bvalid $end
$var reg 32 < rdata [31:0] $end
$var reg 2 = rresp [1:0] $end
$var reg 1 $ rvalid $end
$upscope $end
$upscope $end
$enddefinitions $end
$comment Show the parameter values. $end
$dumpall
b100000 :
b1000 9
$end
#0
$dumpvars
bx =
bx <
bx ;
b1111 8
b0 7
b0 6
b0 5
b0 4
03
b1111 2
b0 1
00
0/
0.
b0 -
0,
0+
b0 *
0)
bx (
x'
bx &
bx %
x$
1#
1"
1!
$end
#5000
b0 &
b0 <
b0 %
b0 =
0$
b0 (
b0 ;
0'
1)
#6000
13
b10100101101001010001001000110100 1
b10100101101001010001001000110100 7
1.
1+
#10000
0)
#15000
1'
1)
#16000
1/
03
0.
#20000
0)
#25000
0'
1)
#26000
1,
0/
#30000
0)
#35000
1$
b10100101101001010001001000110100 &
b10100101101001010001001000110100 <
1)
#36000
10
0,
#40000
0)
#45000
0$
1)
#46000
00
