Peripheral-Configuration-Distribution-Controller/rtl/cdc.v
module cdc (
    input  wire clk,
    input  wire reset,
    input  wire async_in,
    output reg  sync_out
);

    reg sync_ff1;

    always @(posedge clk) begin

        if (reset) begin
            sync_ff1 <= 1'b0;
            sync_out <= 1'b0;
        end

        else begin
            sync_ff1 <= async_in;
            sync_out <= sync_ff1;
        end

    end

endmodule

Peripheral-Configuration-Distribution-Controller/tb/cdc_tb.v
`timescale 1ns/1ps

module cdc_tb;

    reg clk;
    reg reset;
    reg async_in;

    wire sync_out;

    integer errors;

    cdc uut (
        .clk     (clk),
        .reset   (reset),
        .async_in(async_in),
        .sync_out(sync_out)
    );

    always #5 clk = ~clk;

    initial begin

        $dumpfile("sim/waves/cdc.vcd");
        $dumpvars(0, cdc_tb);

        clk = 1'b0;
        reset = 1'b1;
        async_in = 1'b0;
        errors = 0;

        // Reset
        @(posedge clk);
        #1;

        if (sync_out !== 1'b0) begin
            $display("ERROR: CDC output not reset");
            errors = errors + 1;
        end

        reset = 1'b0;

        // Drive input high
        async_in = 1'b1;

        // Two synchronizer stages
        @(posedge clk);
        #1;

        if (sync_out !== 1'b0) begin
            $display("ERROR: CDC synchronized too early");
            errors = errors + 1;
        end

        @(posedge clk);
        #1;

        if (sync_out !== 1'b1) begin
            $display("ERROR: CDC failed to synchronize HIGH");
            errors = errors + 1;
        end
        else begin
            $display("PASS: CDC synchronized HIGH");
        end

        // Drive input low
        async_in = 1'b0;

        @(posedge clk);
        #1;

        if (sync_out !== 1'b1) begin
            $display("ERROR: CDC changed too early");
            errors = errors + 1;
        end

        @(posedge clk);
        #1;

        if (sync_out !== 1'b0) begin
            $display("ERROR: CDC failed to synchronize LOW");
            errors = errors + 1;
        end
        else begin
            $display("PASS: CDC synchronized LOW");
        end

        // Final result
        if (errors == 0) begin
            $display("--------------------------------");
            $display("CDC TEST PASSED");
            $display("--------------------------------");
        end
        else begin
            $display("--------------------------------");
            $display("CDC TEST FAILED: %0d errors", errors);
            $display("--------------------------------");
        end

        $finish;

    end

endmodule

Peripheral-Configuration-Distribution-Controller/sim/waves/cdc.vcd
$date
	Fri Oct  2 01:06:20 2026
$end
$version
	Icarus Verilog
$end
$timescale
	1ps
$end
$scope module cdc_tb $end
$var wire 1 ! sync_out $end
$var reg 1 " async_in $end
$var reg 1 # clk $end
$var reg 1 $ reset $end
$var integer 32 % errors [31:0] $end
$scope module uut $end
$var wire 1 " async_in $end
$var wire 1 # clk $end
$var wire 1 $ reset $end
$var reg 1 & sync_ff1 $end
$var reg 1 ! sync_out $end
$upscope $end
$upscope $end
$enddefinitions $end
$comment Show the parameter values. $end
$dumpall
$end
#0
$dumpvars
x&
b0 %
1$
0#
0"
x!
$end
#5000
0!
0&
1#
#6000
1"
0$
#10000
0#
#15000
1&
1#
#20000
0#
#25000
1!
1#
#26000
0"
#30000
0#
#35000
0&
1#
#40000
0#
#45000
0!
1#
