Peripheral-Configuration-Distribution-Controller/rtl/clock_divider.v
module clock_divider (
    input  wire clk,
    input  wire reset,
    output reg  clk_out
);

    reg [1:0] count;

    always @(posedge clk) begin

        if (reset) begin
            count   <= 2'b00;
            clk_out <= 1'b0;
        end

        else begin

            if (count == 2'd1) begin
                count   <= 2'b00;
                clk_out <= ~clk_out;
            end

            else begin
                count <= count + 1'b1;
            end

        end

    end

endmodule

Peripheral-Configuration-Distribution-Controller/tb/clock_divider_tb.v
`timescale 1ns/1ps

module clock_divider_tb;

    reg clk;
    reg reset;

    wire clk_out;

    integer input_edges;
    integer output_edges;

    clock_divider uut (
        .clk    (clk),
        .reset  (reset),
        .clk_out(clk_out)
    );

    // 10 ns input clock
    always #5 clk = ~clk;

    // Count input clock edges
    always @(posedge clk) begin
        if (!reset)
            input_edges = input_edges + 1;
    end

    // Count output clock edges
    always @(posedge clk_out) begin
        if (!reset)
            output_edges = output_edges + 1;
    end

    initial begin

        $dumpfile("sim/waves/clock_divider.vcd");
        $dumpvars(0, clock_divider_tb);

        clk = 1'b0;
        reset = 1'b1;

        input_edges = 0;
        output_edges = 0;

        // Reset
        #10;

        reset = 1'b0;

        // Run for 100 ns
        #100;

        $display("--------------------------------");
        $display("Clock Divider Simulation Complete");
        $display("Input clock edges : %0d", input_edges);
        $display("Output clock edges: %0d", output_edges);
        $display("--------------------------------");

        $finish;

    end

endmodule

Peripheral-Configuration-Distribution-Controller/sim/waves/clock_divider.vcd
$date
	Tue Sep 29 13:35:12 2026
$end
$version
	Icarus Verilog
$end
$timescale
	1ps
$end
$scope module clock_divider_tb $end
$var wire 1 ! clk_out $end
$var reg 1 " clk $end
$var reg 1 # reset $end
$var integer 32 $ input_edges [31:0] $end
$var integer 32 % output_edges [31:0] $end
$scope module uut $end
$var wire 1 " clk $end
$var wire 1 # reset $end
$var reg 1 ! clk_out $end
$var reg 2 & count [1:0] $end
$upscope $end
$upscope $end
$enddefinitions $end
$comment Show the parameter values. $end
$dumpall
$end
#0
$dumpvars
bx &
b0 %
b0 $
1#
0"
x!
$end
#5000
0!
b0 &
1"
#10000
0"
0#
#15000
b1 &
b1 $
1"
#20000
0"
#25000
b1 %
1!
b0 &
b10 $
1"
#30000
0"
#35000
b1 &
b11 $
1"
#40000
0"
#45000
0!
b0 &
b100 $
1"
#50000
0"
#55000
b1 &
b101 $
1"
#60000
0"
#65000
b10 %
1!
b0 &
b110 $
1"
#70000
0"
#75000
b1 &
b111 $
1"
#80000
0"
#85000
0!
b0 &
b1000 $
1"
#90000
0"
#95000
b1 &
b1001 $
1"
#100000
0"
#105000
b11 %
1!
b0 &
b1010 $
1"
