Peripheral-Configuration-Distribution-Controller/rtl/counter.v
module counter #(
    parameter WIDTH = 4
)(
    input  wire             clk,
    input  wire             reset,
    input  wire             enable,
    output reg  [WIDTH-1:0] count
);

    always @(posedge clk) begin
        if (reset)
            count <= {WIDTH{1'b0}};
        else if (enable)
            count <= count + 1'b1;
    end

endmodule

Peripheral-Configuration-Distribution-Controller/tb/counter_tb.v
`timescale 1ns/1ps

module counter_tb;

    reg clk;
    reg reset;
    reg enable;

    wire [3:0] count;

    integer errors;

    counter #(
        .WIDTH(4)
    ) uut (
        .clk   (clk),
        .reset (reset),
        .enable(enable),
        .count (count)
    );

    always #5 clk = ~clk;

    initial begin

        $dumpfile("sim/waves/counter.vcd");
        $dumpvars(0, counter_tb);

        clk = 1'b0;
        reset = 1'b1;
        enable = 1'b0;
        errors = 0;

        // Reset
        @(posedge clk);
        #1;

        if (count !== 4'd0) begin
            $display("ERROR: Counter did not reset");
            errors = errors + 1;
        end

        reset = 1'b0;

        // Enable counting
        enable = 1'b1;

        repeat (5) begin
            @(posedge clk);
            #1;
        end

        if (count !== 4'd5) begin
            $display("ERROR: Expected count=5, Got=%0d", count);
            errors = errors + 1;
        end
        else begin
            $display("PASS: Counter reached 5");
        end

        // Disable counting
        enable = 1'b0;

        @(posedge clk);
        #1;

        if (count !== 4'd5) begin
            $display("ERROR: Counter changed while disabled");
            errors = errors + 1;
        end
        else begin
            $display("PASS: Counter held value when disabled");
        end

        // Final result
        if (errors == 0) begin
            $display("--------------------------------");
            $display("COUNTER TEST PASSED");
            $display("--------------------------------");
        end
        else begin
            $display("--------------------------------");
            $display("COUNTER TEST FAILED: %0d errors", errors);
            $display("--------------------------------");
        end

        $finish;

    end

endmodule

Peripheral-Configuration-Distribution-Controller/sim/waves/counter.vcd
$date
	Fri Oct  2 01:06:20 2026
$end
$version
	Icarus Verilog
$end
$timescale
	1ps
$end
$scope module counter_tb $end
$var wire 4 ! count [3:0] $end
$var reg 1 " clk $end
$var reg 1 # enable $end
$var reg 1 $ reset $end
$var integer 32 % errors [31:0] $end
$scope module uut $end
$var wire 1 " clk $end
$var wire 1 # enable $end
$var wire 1 $ reset $end
$var parameter 32 & WIDTH $end
$var reg 4 ' count [3:0] $end
$upscope $end
$upscope $end
$enddefinitions $end
$comment Show the parameter values. $end
$dumpall
b100 &
$end
#0
$dumpvars
bx '
b0 %
1$
0#
0"
bx !
$end
#5000
b0 !
b0 '
1"
#6000
1#
0$
#10000
0"
#15000
b1 !
b1 '
1"
#20000
0"
#25000
b10 !
b10 '
1"
#30000
0"
#35000
b11 !
b11 '
1"
#40000
0"
#45000
b100 !
b100 '
1"
#50000
0"
#55000
b101 !
b101 '
1"
#56000
0#
