Peripheral-Configuration-Distribution-Controller/rtl/memory.v
module memory #(
    parameter DATA_WIDTH = 8,
    parameter ADDR_WIDTH = 4
)(
    input  wire                  clk,
    input  wire                  reset,

    input  wire                  write_en,
    input  wire [ADDR_WIDTH-1:0] address,
    input  wire [DATA_WIDTH-1:0] write_data,

    output reg  [DATA_WIDTH-1:0] read_data
);

    reg [DATA_WIDTH-1:0] mem [0:(1 << ADDR_WIDTH)-1];

    integer i;

    always @(posedge clk) begin

        if (reset) begin
            read_data <= {DATA_WIDTH{1'b0}};

            for (i = 0; i < (1 << ADDR_WIDTH); i = i + 1)
                mem[i] <= {DATA_WIDTH{1'b0}};
        end

        else begin

            if (write_en)
                mem[address] <= write_data;

            read_data <= mem[address];

        end

    end

endmodule

Peripheral-Configuration-Distribution-Controller/tb/memory_tb.v
`timescale 1ns/1ps

module memory_tb;

    reg clk;
    reg reset;

    reg write_en;
    reg [3:0] address;
    reg [7:0] write_data;

    wire [7:0] read_data;

    integer errors;

    memory #(
        .DATA_WIDTH(8),
        .ADDR_WIDTH(4)
    ) uut (
        .clk      (clk),
        .reset    (reset),
        .write_en (write_en),
        .address  (address),
        .write_data(write_data),
        .read_data(read_data)
    );

    always #5 clk = ~clk;

    initial begin

        $dumpfile("sim/waves/memory.vcd");
        $dumpvars(0, memory_tb);

        clk = 1'b0;
        reset = 1'b1;

        write_en = 1'b0;
        address = 4'b0;
        write_data = 8'b0;

        errors = 0;

        // Reset
        @(posedge clk);
        #1;

        reset = 1'b0;

        // ------------------------------------------------
        // Write 0xA5 to address 3
        // ------------------------------------------------

        address = 4'd3;
        write_data = 8'hA5;
        write_en = 1'b1;

        @(posedge clk);
        #1;

        write_en = 1'b0;

        // ------------------------------------------------
        // Read address 3
        // ------------------------------------------------

        @(posedge clk);
        #1;

        if (read_data !== 8'hA5) begin
            $display(
                "ERROR: Expected=0xA5 | Got=0x%h",
                read_data
            );
            errors = errors + 1;
        end
        else begin
            $display("PASS: Correct data read from address 3");
        end

        // ------------------------------------------------
        // Write another value
        // ------------------------------------------------

        address = 4'd7;
        write_data = 8'h5A;
        write_en = 1'b1;

        @(posedge clk);
        #1;

        write_en = 1'b0;

        // Read address 7
        @(posedge clk);
        #1;

        if (read_data !== 8'h5A) begin
            $display(
                "ERROR: Expected=0x5A | Got=0x%h",
                read_data
            );
            errors = errors + 1;
        end
        else begin
            $display("PASS: Correct data read from address 7");
        end

        // ------------------------------------------------
        // Final result
        // ------------------------------------------------

        if (errors == 0) begin
            $display("--------------------------------");
            $display("MEMORY TEST PASSED");
            $display("--------------------------------");
        end
        else begin
            $display("--------------------------------");
            $display("MEMORY TEST FAILED: %0d errors", errors);
            $display("--------------------------------");
        end

        $finish;

    end

endmodule

Peripheral-Configuration-Distribution-Controller/sim/waves/memory.vcd
$date
	Tue Sep 29 13:27:47 2026
$end
$version
	Icarus Verilog
$end
$timescale
	1ps
$end
$scope module memory_tb $end
$var wire 8 ! read_data [7:0] $end
$var reg 4 " address [3:0] $end
$var reg 1 # clk $end
$var reg 1 $ reset $end
$var reg 8 % write_data [7:0] $end
$var reg 1 & write_en $end
$var integer 32 ' errors [31:0] $end
$scope module uut $end
$var wire 4 ( address [3:0] $end
$var wire 1 # clk $end
$var wire 1 $ reset $end
$var wire 8 ) write_data [7:0] $end
$var wire 1 & write_en $end
$var parameter 32 * ADDR_WIDTH $end
$var parameter 32 + DATA_WIDTH $end
$var reg 8 , read_data [7:0] $end
$var integer 32 - i [31:0] $end
$upscope $end
$upscope $end
$enddefinitions $end
$comment Show the parameter values. $end
$dumpall
b1000 +
b100 *
$end
#0
$dumpvars
bx -
bx ,
b0 )
b0 (
b0 '
0&
b0 %
1$
0#
b0 "
bx !
$end
#5000
b0 !
b0 ,
b10000 -
1#
#6000
1&
b10100101 %
b10100101 )
b11 "
b11 (
0$
#10000
0#
#15000
1#
#16000
0&
#20000
0#
#25000
b10100101 !
b10100101 ,
1#
#26000
1&
b1011010 %
b1011010 )
b111 "
b111 (
#30000
0#
#35000
b0 !
b0 ,
1#
#36000
0&
#40000
0#
#45000
b1011010 !
b1011010 ,
1#
