Peripheral-Configuration-Distribution-Controller/rtl/clock_divider.v
module clock_divider (
    input  wire clk,
    input  wire reset,
    output reg  clk_out
);

    reg [1:0] count;

    always @(posedge clk) begin

        if (reset) begin
            count   <= 2'b00;
            clk_out <= 1'b0;
        end

        else begin

            if (count == 2'd1) begin
                count   <= 2'b00;
                clk_out <= ~clk_out;
            end

            else begin
                count <= count + 1'b1;
            end

        end

    end

endmodule

Peripheral-Configuration-Distribution-Controller/rtl/peripheral_controller.v
module peripheral_controller (
    input  wire       clk,
    input  wire       reset,
    input  wire       start,
    input  wire [7:0] tx_data,
    input  wire       miso,

    output reg       mosi,
    output reg       sclk,
    output reg       cs,

    output reg [7:0] rx_data,
    output reg       busy,
    output reg       done
);

    reg [7:0] tx_shift;
    reg [7:0] rx_shift;
    reg [3:0] bit_count;

    wire spi_clk;

    // --------------------------------------------------
    // SPI clock divider
    // CPU clock -> SPI clock /4
    // --------------------------------------------------

    clock_divider clk_div (
        .clk     (clk),
        .reset   (reset),
        .clk_out (spi_clk)
    );

    // --------------------------------------------------
    // SPI controller
    // --------------------------------------------------

    always @(posedge clk) begin

        if (reset) begin

            tx_shift  <= 8'b0;
            rx_shift  <= 8'b0;
            bit_count <= 4'd0;

            mosi <= 1'b0;
            sclk <= 1'b0;
            cs   <= 1'b1;

            rx_data <= 8'b0;
            busy    <= 1'b0;
            done    <= 1'b0;

        end else begin

            done <= 1'b0;

            // ------------------------------------------
            // Start transaction
            // ------------------------------------------

            if (start && !busy) begin

                tx_shift  <= tx_data;
                rx_shift  <= 8'b0;
                bit_count <= 4'd0;

                mosi <= tx_data[7];
                sclk <= 1'b0;
                cs   <= 1'b0;

                busy <= 1'b1;

            end

            // ------------------------------------------
            // SPI transaction
            // ------------------------------------------

            else if (busy && spi_clk) begin

                // --------------------------------------
                // Rising SPI edge
                // Sample MISO
                // --------------------------------------

                if (sclk == 1'b0) begin

                    sclk <= 1'b1;

                    rx_shift <= {
                        rx_shift[6:0],
                        miso
                    };

                end

                // --------------------------------------
                // Falling SPI edge
                // Shift TX
                // --------------------------------------

                else begin

                    sclk <= 1'b0;

                    if (bit_count == 4'd7) begin

                        rx_data <= rx_shift;

                        mosi <= 1'b0;
                        cs   <= 1'b1;

                        busy <= 1'b0;
                        done <= 1'b1;

                    end else begin

                        bit_count <= bit_count + 1'b1;

                        tx_shift <= {
                            tx_shift[6:0],
                            1'b0
                        };

                        mosi <= tx_shift[6];

                    end

                end

            end

        end

    end

endmodule

Peripheral-Configuration-Distribution-Controller/tb/peripheral_controller_tb.v
`timescale 1ns/1ps

module peripheral_controller_tb;

    reg        clk;
    reg        reset;
    reg        start;
    reg [7:0]  tx_data;
    reg        miso;

    wire       mosi;
    wire       sclk;
    wire       cs;

    wire [7:0] rx_data;
    wire       busy;
    wire       done;

    reg [7:0] slave_tx_data;
    reg [7:0] slave_rx_data;

    integer bit_count;
    integer errors;

    // --------------------------------------------------
    // DUT
    // --------------------------------------------------

    peripheral_controller uut (
        .clk     (clk),
        .reset   (reset),
        .start   (start),
        .tx_data (tx_data),
        .miso    (miso),

        .mosi    (mosi),
        .sclk    (sclk),
        .cs      (cs),

        .rx_data (rx_data),
        .busy    (busy),
        .done    (done)
    );

    // --------------------------------------------------
    // CPU clock
    // --------------------------------------------------

    always #5 clk = ~clk;

    // --------------------------------------------------
    // Simulated SPI slave
    //
    // Slave changes MISO on the falling edge.
    // Controller samples MISO on rising edge.
    // --------------------------------------------------

    always @(negedge sclk) begin

        if (!cs) begin
            miso <= slave_tx_data[7-bit_count];
        end

    end

    // --------------------------------------------------
    // Slave receives MOSI on rising edge
    // --------------------------------------------------

    always @(posedge sclk) begin

        if (!cs) begin

            slave_rx_data[7-bit_count] = mosi;

            if (bit_count < 7)
                bit_count = bit_count + 1;
            else
                bit_count = 0;

        end

    end

    // --------------------------------------------------
    // Test
    // --------------------------------------------------

    initial begin

        $dumpfile("sim/waves/peripheral_controller.vcd");
        $dumpvars(0, peripheral_controller_tb);

        clk = 1'b0;
        reset = 1'b1;

        start = 1'b0;
        tx_data = 8'b0;

        miso = 1'b0;

        slave_tx_data = 8'b01100101;
        slave_rx_data = 8'b0;

        bit_count = 0;
        errors = 0;

        // --------------------------------------------------
        // Reset
        // --------------------------------------------------

        #20;

        reset = 1'b0;

        // --------------------------------------------------
        // Prepare transaction
        // --------------------------------------------------

        tx_data = 8'b10100101;

        #10;

        start = 1'b1;

        @(posedge clk);
        #1;

        start = 1'b0;

        // --------------------------------------------------
        // Check transaction started
        // --------------------------------------------------

        if (busy !== 1'b1) begin
            $display("ERROR: Controller did not start");
            errors = errors + 1;
        end
        else begin
            $display("PASS: Controller transaction started");
        end

        if (cs !== 1'b0) begin
            $display("ERROR: CS not asserted");
            errors = errors + 1;
        end
        else begin
            $display("PASS: CS asserted");
        end

        // --------------------------------------------------
        // Wait until transaction finishes
        // --------------------------------------------------

        wait(done == 1'b1);

        #5;

        // --------------------------------------------------
        // Verify received data
        // --------------------------------------------------

        if (rx_data !== slave_tx_data) begin

            $display(
                "ERROR: RX DATA | Expected=%b | Got=%b",
                slave_tx_data,
                rx_data
            );

            errors = errors + 1;

        end
        else begin

            $display("PASS: Correct RX data received");

        end

        // --------------------------------------------------
        // Verify transmitted data
        // --------------------------------------------------

        if (slave_rx_data !== tx_data) begin

            $display(
                "ERROR: TX DATA | Expected=%b | Got=%b",
                tx_data,
                slave_rx_data
            );

            errors = errors + 1;

        end
        else begin

            $display("PASS: Correct TX data transmitted");

        end

        // --------------------------------------------------
        // Verify completion
        // --------------------------------------------------

        if (busy !== 1'b0) begin

            $display("ERROR: BUSY did not deassert");

            errors = errors + 1;

        end
        else begin

            $display("PASS: BUSY deasserted");

        end

        if (cs !== 1'b1) begin

            $display("ERROR: CS did not deassert");

            errors = errors + 1;

        end
        else begin

            $display("PASS: CS deasserted");

        end

        // --------------------------------------------------
        // Final result
        // --------------------------------------------------

        if (errors == 0) begin

            $display("--------------------------------");
            $display("PERIPHERAL CONTROLLER TEST PASSED");
            $display("--------------------------------");

        end
        else begin

            $display("--------------------------------");
            $display(
                "PERIPHERAL CONTROLLER TEST FAILED: %0d errors",
                errors
            );
            $display("--------------------------------");

        end

        $finish;

    end

endmodule

Peripheral-Configuration-Distribution-Controller/sim/waves/peripheral_controller.vcd
$date
	Fri Oct  2 01:07:12 2026
$end
$version
	Icarus Verilog
$end
$timescale
	1ps
$end
$scope module peripheral_controller_tb $end
$var wire 1 ! sclk $end
$var wire 8 " rx_data [7:0] $end
$var wire 1 # mosi $end
$var wire 1 $ done $end
$var wire 1 % cs $end
$var wire 1 & busy $end
$var reg 1 ' clk $end
$var reg 1 ( miso $end
$var reg 1 ) reset $end
$var reg 8 * slave_rx_data [7:0] $end
$var reg 8 + slave_tx_data [7:0] $end
$var reg 1 , start $end
$var reg 8 - tx_data [7:0] $end
$var integer 32 . bit_count [31:0] $end
$var integer 32 / errors [31:0] $end
$scope module uut $end
$var wire 1 ' clk $end
$var wire 1 ( miso $end
$var wire 1 ) reset $end
$var wire 1 , start $end
$var wire 8 0 tx_data [7:0] $end
$var wire 1 1 spi_clk $end
$var reg 4 2 bit_count [3:0] $end
$var reg 1 & busy $end
$var reg 1 % cs $end
$var reg 1 $ done $end
$var reg 1 # mosi $end
$var reg 8 3 rx_data [7:0] $end
$var reg 8 4 rx_shift [7:0] $end
$var reg 1 ! sclk $end
$var reg 8 5 tx_shift [7:0] $end
$scope module clk_div $end
$var wire 1 ' clk $end
$var wire 1 ) reset $end
$var reg 1 1 clk_out $end
$var reg 2 6 count [1:0] $end
$upscope $end
$upscope $end
$upscope $end
$enddefinitions $end
$comment Show the parameter values. $end
$dumpall
$end
#0
$dumpvars
bx 6
bx 5
bx 4
bx 3
bx 2
x1
b0 0
b0 /
b0 .
b0 -
0,
b1100101 +
b0 *
1)
0(
0'
x&
x%
x$
x#
bx "
x!
$end
#5000
01
b0 6
0$
0&
b0 "
b0 3
1%
0!
0#
b0 2
b0 4
b0 5
1'
#10000
0'
#15000
1'
#20000
0'
b10100101 -
b10100101 0
0)
#25000
b1 6
1'
#30000
0'
1,
#35000
1&
0%
1#
b10100101 5
11
b0 6
1'
#36000
0,
#40000
0'
#45000
b1 .
b10000000 *
b1 6
1!
1'
#50000
0'
#55000
1(
0#
b1001010 5
b1 2
0!
01
b0 6
1'
#60000
0'
#65000
b1 6
1'
#70000
0'
#75000
11
b0 6
1'
#80000
0'
#85000
b10 .
b1 6
b1 4
1!
1'
#90000
0'
#95000
1#
b10010100 5
b10 2
0!
01
b0 6
1'
#100000
0'
#105000
b1 6
1'
#110000
0'
#115000
11
b0 6
1'
#120000
0'
#125000
b11 .
b10100000 *
b1 6
b11 4
1!
1'
#130000
0'
#135000
0(
0#
b101000 5
b11 2
0!
01
b0 6
1'
#140000
0'
#145000
b1 6
1'
#150000
0'
#155000
11
b0 6
1'
#160000
0'
#165000
b100 .
b1 6
b110 4
1!
1'
#170000
0'
#175000
b1010000 5
b100 2
0!
01
b0 6
1'
#180000
0'
#185000
b1 6
1'
#190000
0'
#195000
11
b0 6
1'
#200000
0'
#205000
b101 .
b1 6
b1100 4
1!
1'
#210000
0'
#215000
1(
1#
b10100000 5
b101 2
0!
01
b0 6
1'
#220000
0'
#225000
b1 6
1'
#230000
0'
#235000
11
b0 6
1'
#240000
0'
#245000
b110 .
b10100100 *
b1 6
b11001 4
1!
1'
#250000
0'
#255000
0(
0#
b1000000 5
b110 2
0!
01
b0 6
1'
#260000
0'
#265000
b1 6
1'
#270000
0'
#275000
11
b0 6
1'
#280000
0'
#285000
b111 .
b1 6
b110010 4
1!
1'
#290000
0'
#295000
1(
1#
b10000000 5
b111 2
0!
01
b0 6
1'
#300000
0'
#305000
b1 6
1'
#310000
0'
#315000
11
b0 6
1'
#320000
0'
#325000
b0 .
b10100101 *
b1 6
b1100101 4
1!
1'
#330000
0'
#335000
1$
0&
1%
0#
b1100101 "
b1100101 3
0!
01
b0 6
1'
