Peripheral-Configuration-Distribution-Controller/rtl/piso.v
module piso (
    input  wire       clk,
    input  wire       reset,
    input  wire       load,
    input  wire [7:0] parallel_in,
    output reg        serial_out,
    output reg        valid
);

    reg [7:0] shift_reg;
    reg [2:0] bit_count;

    always @(posedge clk) begin

        if (reset) begin
            shift_reg  <= 8'b0;
            bit_count  <= 3'b0;
            serial_out <= 1'b0;
            valid      <= 1'b0;
        end

        else if (load) begin
            shift_reg  <= parallel_in;
            bit_count  <= 3'b0;
            serial_out <= parallel_in[0];
            valid      <= 1'b0;
        end

        else begin
            valid <= 1'b0;

            if (bit_count < 3'd7) begin
                shift_reg  <= shift_reg >> 1;
                bit_count  <= bit_count + 1'b1;
                serial_out <= shift_reg[1];
            end

            else begin
                shift_reg  <= shift_reg >> 1;
                bit_count  <= 3'b0;
                serial_out <= shift_reg[7];
                valid      <= 1'b1;
            end
        end

    end

endmodule

Peripheral-Configuration-Distribution-Controller/tb/piso_tb.v
`timescale 1ns/1ps

module piso_tb;

    reg       clk;
    reg       reset;
    reg       load;
    reg [7:0] parallel_in;

    wire      serial_out;
    wire      valid;

    integer i;
    integer errors;

    reg [7:0] test_data;
    reg [7:0] expected_data;

    piso uut (
        .clk        (clk),
        .reset      (reset),
        .load       (load),
        .parallel_in(parallel_in),
        .serial_out (serial_out),
        .valid      (valid)
    );

    // 10 ns clock period
    always #5 clk = ~clk;

    initial begin

        $dumpfile("sim/waves/piso.vcd");
        $dumpvars(0, piso_tb);

        errors = 0;

        clk         = 1'b0;
        reset       = 1'b1;
        load        = 1'b0;
        parallel_in = 8'b0;

        // Reset
        @(posedge clk);
        #1;

        reset = 1'b0;

        // ------------------------------------------------
        // Test 1
        // ------------------------------------------------

        test_data = 8'b10110010;
        expected_data = test_data;

        parallel_in = test_data;
        load = 1'b1;

        @(posedge clk);
        #1;

        load = 1'b0;

        // Check 8 transmitted bits
        for (i = 0; i < 8; i = i + 1) begin

            #1;

            if (serial_out !== expected_data[i]) begin
                $display(
                    "ERROR: Bit %0d | Expected=%b | Got=%b",
                    i,
                    expected_data[i],
                    serial_out
                );
                errors = errors + 1;
            end

            @(posedge clk);
        end

        #1;

        if (valid !== 1'b1) begin
            $display("ERROR: valid was not asserted after 8 bits");
            errors = errors + 1;
        end

        else begin
            $display("PASS: First 8-bit transmission");
        end

        @(posedge clk);
        #1;

        if (valid !== 1'b0) begin
            $display("ERROR: valid did not return low");
            errors = errors + 1;
        end

        // ------------------------------------------------
        // Test 2 - second byte
        // ------------------------------------------------

        test_data = 8'b01100101;
        expected_data = test_data;

        parallel_in = test_data;
        load = 1'b1;

        @(posedge clk);
        #1;

        load = 1'b0;

        for (i = 0; i < 8; i = i + 1) begin

            #1;

            if (serial_out !== expected_data[i]) begin
                $display(
                    "ERROR: Second transmission - Bit %0d | Expected=%b | Got=%b",
                    i,
                    expected_data[i],
                    serial_out
                );
                errors = errors + 1;
            end

            @(posedge clk);
        end

        #1;

        if (valid !== 1'b1) begin
            $display("ERROR: valid was not asserted for second transmission");
            errors = errors + 1;
        end
        else begin
            $display("PASS: Second 8-bit transmission");
        end

        // ------------------------------------------------
        // Final result
        // ------------------------------------------------

        @(posedge clk);
        #1;

        if (errors == 0) begin
            $display("--------------------------------");
            $display("PISO TEST PASSED");
            $display("--------------------------------");
        end
        else begin
            $display("--------------------------------");
            $display("PISO TEST FAILED: %0d errors", errors);
            $display("--------------------------------");
        end

        $finish;

    end

endmodule

Peripheral-Configuration-Distribution-Controller/sim/waves/piso.vcd
$date
	Tue Sep 29 14:17:13 2026
$end
$version
	Icarus Verilog
$end
$timescale
	1ps
$end
$scope module piso_tb $end
$var wire 1 ! valid $end
$var wire 1 " serial_out $end
$var reg 1 # clk $end
$var reg 8 $ expected_data [7:0] $end
$var reg 1 % load $end
$var reg 8 & parallel_in [7:0] $end
$var reg 1 ' reset $end
$var reg 8 ( test_data [7:0] $end
$var integer 32 ) errors [31:0] $end
$var integer 32 * i [31:0] $end
$scope module uut $end
$var wire 1 # clk $end
$var wire 1 % load $end
$var wire 8 + parallel_in [7:0] $end
$var wire 1 ' reset $end
$var reg 3 , bit_count [2:0] $end
$var reg 1 " serial_out $end
$var reg 8 - shift_reg [7:0] $end
$var reg 1 ! valid $end
$upscope $end
$upscope $end
$enddefinitions $end
$comment Show the parameter values. $end
$dumpall
$end
#0
$dumpvars
bx -
bx ,
b0 +
bx *
b0 )
bx (
1'
b0 &
0%
bx $
0#
x"
x!
$end
#5000
0!
0"
b0 ,
b0 -
1#
#6000
1%
b10110010 &
b10110010 +
b10110010 $
b10110010 (
0'
#10000
0#
#15000
b10110010 -
1#
#16000
b0 *
0%
#20000
0#
#25000
1"
b1 ,
b1011001 -
b1 *
1#
#30000
0#
#35000
0"
b10 ,
b101100 -
b10 *
1#
#40000
0#
#45000
b11 ,
b10110 -
b11 *
1#
#50000
0#
#55000
1"
b100 ,
b1011 -
b100 *
1#
#60000
0#
#65000
b101 ,
b101 -
b101 *
1#
#70000
0#
#75000
0"
b110 ,
b10 -
b110 *
1#
#80000
0#
#85000
1"
b111 ,
b1 -
b111 *
1#
#90000
0#
#95000
1!
0"
b0 ,
b0 -
b1000 *
1#
#100000
0#
#105000
b1 ,
0!
1#
#106000
1%
b1100101 &
b1100101 +
b1100101 $
b1100101 (
#110000
0#
#115000
1"
b0 ,
b1100101 -
1#
#116000
b0 *
0%
#120000
0#
#125000
0"
b1 ,
b110010 -
b1 *
1#
#130000
0#
#135000
1"
b10 ,
b11001 -
b10 *
1#
#140000
0#
#145000
0"
b11 ,
b1100 -
b11 *
1#
#150000
0#
#155000
b100 ,
b110 -
b100 *
1#
#160000
0#
#165000
1"
b101 ,
b11 -
b101 *
1#
#170000
0#
#175000
b110 ,
b1 -
b110 *
1#
#180000
0#
#185000
0"
b111 ,
b0 -
b111 *
1#
#190000
0#
#195000
1!
b0 ,
b1000 *
1#
#200000
0#
#205000
b1 ,
0!
1#
