Peripheral-Configuration-Distribution-Controller/rtl/sipo.v
module sipo (
    input  wire       clk,
    input  wire       reset,
    input  wire       enable,
    input  wire       serial_in,
    output reg  [7:0] parallel_out,
    output reg        valid
);

    reg [7:0] shift_reg;
    reg [2:0] bit_count;

    always @(posedge clk) begin

        if (reset) begin
            shift_reg   <= 8'b0;
            parallel_out <= 8'b0;
            bit_count   <= 3'b0;
            valid       <= 1'b0;
        end

        else begin

            valid <= 1'b0;

            if (enable) begin

                if (bit_count < 3'd7) begin
                    shift_reg <= {serial_in, shift_reg[7:1]};
                    bit_count <= bit_count + 1'b1;
                end

                else begin
                    shift_reg <= {serial_in, shift_reg[7:1]};

                    parallel_out <= {serial_in, shift_reg[7:1]};

                    bit_count <= 3'b0;
                    valid <= 1'b1;
                end

            end

        end

    end

endmodule

Peripheral-Configuration-Distribution-Controller/tb/sipo_tb.v
`timescale 1ns/1ps

module sipo_tb;

    reg       clk;
    reg       reset;
    reg       enable;
    reg       serial_in;

    wire [7:0] parallel_out;
    wire      valid;

    integer i;
    integer errors;

    reg [7:0] test_data;

    sipo uut (
        .clk         (clk),
        .reset       (reset),
        .enable      (enable),
        .serial_in   (serial_in),
        .parallel_out(parallel_out),
        .valid       (valid)
    );

    // 10 ns clock period
    always #5 clk = ~clk;

    initial begin

        $dumpfile("sim/waves/sipo.vcd");
        $dumpvars(0, sipo_tb);

        errors = 0;

        clk       = 1'b0;
        reset     = 1'b1;
        enable    = 1'b0;
        serial_in = 1'b0;

        // Reset
        @(posedge clk);
        #1;

        reset = 1'b0;

        // Test data
        test_data = 8'b10110010;

        enable = 1'b1;

        // Send LSB first
        for (i = 0; i < 8; i = i + 1) begin

            serial_in = test_data[i];

            @(posedge clk);
            #1;

        end

        enable = 1'b0;

        // Check received data
        if (parallel_out !== test_data) begin

            $display(
                "ERROR: Expected=%b | Got=%b",
                test_data,
                parallel_out
            );

            errors = errors + 1;

        end

        else begin
            $display("PASS: SIPO received correct parallel data");
        end

        // Check valid
        if (valid !== 1'b1) begin
            $display("ERROR: valid was not asserted");
            errors = errors + 1;
        end

        else begin
            $display("PASS: valid asserted after 8 bits");
        end

        @(posedge clk);
        #1;

        if (valid !== 1'b0) begin
            $display("ERROR: valid did not return low");
            errors = errors + 1;
        end

        // Final result
        if (errors == 0) begin
            $display("--------------------------------");
            $display("SIPO TEST PASSED");
            $display("--------------------------------");
        end
        else begin
            $display("--------------------------------");
            $display("SIPO TEST FAILED: %0d errors", errors);
            $display("--------------------------------");
        end

        $finish;

    end

endmodule

Peripheral-Configuration-Distribution-Controller/sim/waves/sipo.vcd
$date
	Tue Sep 29 13:35:12 2026
$end
$version
	Icarus Verilog
$end
$timescale
	1ps
$end
$scope module sipo_tb $end
$var wire 1 ! valid $end
$var wire 8 " parallel_out [7:0] $end
$var reg 1 # clk $end
$var reg 1 $ enable $end
$var reg 1 % reset $end
$var reg 1 & serial_in $end
$var reg 8 ' test_data [7:0] $end
$var integer 32 ( errors [31:0] $end
$var integer 32 ) i [31:0] $end
$scope module uut $end
$var wire 1 # clk $end
$var wire 1 $ enable $end
$var wire 1 % reset $end
$var wire 1 & serial_in $end
$var reg 3 * bit_count [2:0] $end
$var reg 8 + parallel_out [7:0] $end
$var reg 8 , shift_reg [7:0] $end
$var reg 1 ! valid $end
$upscope $end
$upscope $end
$enddefinitions $end
$comment Show the parameter values. $end
$dumpall
$end
#0
$dumpvars
bx ,
bx +
bx *
bx )
b0 (
bx '
0&
1%
0$
0#
bx "
x!
$end
#5000
0!
b0 *
b0 "
b0 +
b0 ,
1#
#6000
b0 )
1$
b10110010 '
0%
#10000
0#
#15000
b1 *
1#
#16000
1&
b1 )
#20000
0#
#25000
b10 *
b10000000 ,
1#
#26000
0&
b10 )
#30000
0#
#35000
b11 *
b1000000 ,
1#
#36000
b11 )
#40000
0#
#45000
b100 *
b100000 ,
1#
#46000
1&
b100 )
#50000
0#
#55000
b101 *
b10010000 ,
1#
#56000
b101 )
#60000
0#
#65000
b110 *
b11001000 ,
1#
#66000
0&
b110 )
#70000
0#
#75000
b111 *
b1100100 ,
1#
#76000
1&
b111 )
#80000
0#
#85000
1!
b0 *
b10110010 "
b10110010 +
b10110010 ,
1#
#86000
0$
b1000 )
#90000
0#
#95000
0!
1#
