Peripheral-Configuration-Distribution-Controller/rtl/spi_master.v
module spi_master (
    input  wire       clk,
    input  wire       reset,

    input  wire       start,
    input  wire [7:0] tx_data,
    input  wire       miso,

    output reg        mosi,
    output reg        sclk,
    output reg        cs,

    output reg [7:0]  rx_data,
    output reg        busy,
    output reg        done
);

    reg [7:0] tx_shift;
    reg [7:0] rx_shift;
    reg [2:0] bit_count;

    always @(posedge clk) begin

        if (reset) begin
            tx_shift <= 8'b0;
            rx_shift <= 8'b0;
            rx_data  <= 8'b0;

            bit_count <= 3'b0;

            mosi <= 1'b0;
            sclk <= 1'b0;
            cs   <= 1'b1;

            busy <= 1'b0;
            done <= 1'b0;
        end

        else begin

            done <= 1'b0;

            // Start a new transaction
            if (start && !busy) begin

                tx_shift <= tx_data;
                rx_shift <= 8'b0;

                bit_count <= 3'd0;

                // Send first LSB
                mosi <= tx_data[0];

                cs   <= 1'b0;
                sclk <= 1'b0;

                busy <= 1'b1;
            end

            else if (busy) begin

                // Toggle SPI clock
                sclk <= ~sclk;

                // Rising edge: sample MISO
                if (sclk == 1'b0) begin

                    rx_shift <= {miso, rx_shift[7:1]};

                end

                // Falling edge: prepare next MOSI bit
                else begin

                    if (bit_count == 3'd7) begin

                        // Include the final sampled MISO bit
                        rx_data <= {miso, rx_shift[7:1]};

                        cs   <= 1'b1;
                        sclk <= 1'b0;

                        busy <= 1'b0;
                        done <= 1'b1;

                        mosi <= 1'b0;

                    end

                    else begin

                        bit_count <= bit_count + 1'b1;

                        tx_shift <= tx_shift >> 1;

                        mosi <= tx_shift[1];

                    end

                end

            end

        end

    end

endmodule

Peripheral-Configuration-Distribution-Controller/tb/spi_master_tb.v
`timescale 1ns/1ps

module spi_master_tb;

    reg clk;
    reg reset;

    reg start;
    reg [7:0] tx_data;
    reg miso;

    wire mosi;
    wire sclk;
    wire cs;

    wire [7:0] rx_data;
    wire busy;
    wire done;

    integer errors;
    integer i;

    reg [7:0] expected_tx;
    reg [7:0] expected_rx;

    spi_master uut (
        .clk    (clk),
        .reset  (reset),
        .start  (start),
        .tx_data(tx_data),
        .miso   (miso),
        .mosi   (mosi),
        .sclk   (sclk),
        .cs     (cs),
        .rx_data(rx_data),
        .busy   (busy),
        .done   (done)
    );

    always #5 clk = ~clk;

    initial begin

        $dumpfile("sim/waves/spi_master.vcd");
        $dumpvars(0, spi_master_tb);

        clk = 1'b0;
        reset = 1'b1;
        start = 1'b0;
        tx_data = 8'b0;
        miso = 1'b0;

        errors = 0;

        // Reset
        @(posedge clk);
        #1;

        if (cs !== 1'b1) begin
            $display("ERROR: CS not high after reset");
            errors = errors + 1;
        end

        if (busy !== 1'b0) begin
            $display("ERROR: BUSY not low after reset");
            errors = errors + 1;
        end

        reset = 1'b0;

        // ------------------------------------------------
        // Start SPI transaction
        // ------------------------------------------------

        expected_tx = 8'b10110010;
        expected_rx = 8'b01100101;

        tx_data = expected_tx;

        start = 1'b1;

        @(posedge clk);
        #1;

        start = 1'b0;

        if (busy !== 1'b1) begin
            $display("ERROR: BUSY not asserted");
            errors = errors + 1;
        end
        else begin
            $display("PASS: SPI transaction started");
        end

        if (cs !== 1'b0) begin
            $display("ERROR: CS not asserted");
            errors = errors + 1;
        end
        else begin
            $display("PASS: CS asserted");
        end

        // ------------------------------------------------
        // Full-duplex transfer
        // ------------------------------------------------
        //
        // The DUT samples MISO during the low-to-high
        // portion of SCLK. Change MISO before each
        // sampling edge.
        //
        // LSB first
        // ------------------------------------------------

        for (i = 0; i < 8; i = i + 1) begin

            miso = expected_rx[i];

            // Wait for SCLK rising edge
            @(posedge sclk);
            #1;

            if (i == 0) begin
                $display("PASS: SPI clock started");
            end

        end

        // Allow DUT to finish transaction
        wait(done == 1'b1);
        #1;

        // ------------------------------------------------
        // Check received data
        // ------------------------------------------------

        if (rx_data !== expected_rx) begin

            $display(
                "ERROR: RX data | Expected=%b | Got=%b",
                expected_rx,
                rx_data
            );

            errors = errors + 1;

        end
        else begin
            $display("PASS: Correct RX data received");
        end

        // ------------------------------------------------
        // Check transaction completion
        // ------------------------------------------------

        if (busy !== 1'b0) begin
            $display("ERROR: BUSY did not deassert");
            errors = errors + 1;
        end
        else begin
            $display("PASS: BUSY deasserted");
        end

        if (cs !== 1'b1) begin
            $display("ERROR: CS did not deassert");
            errors = errors + 1;
        end
        else begin
            $display("PASS: CS deasserted");
        end

        if (done !== 1'b1) begin
            $display("ERROR: DONE not asserted");
            errors = errors + 1;
        end
        else begin
            $display("PASS: DONE asserted");
        end

        // ------------------------------------------------
        // Final result
        // ------------------------------------------------

        if (errors == 0) begin
            $display("--------------------------------");
            $display("SPI MASTER TEST PASSED");
            $display("--------------------------------");
        end
        else begin
            $display("--------------------------------");
            $display("SPI MASTER TEST FAILED: %0d errors", errors);
            $display("--------------------------------");
        end

        $finish;

    end

endmodule

Peripheral-Configuration-Distribution-Controller/sim/waves/spi_master.vcd
$date
	Tue Sep 29 13:30:01 2026
$end
$version
	Icarus Verilog
$end
$timescale
	1ps
$end
$scope module spi_master_tb $end
$var wire 1 ! sclk $end
$var wire 8 " rx_data [7:0] $end
$var wire 1 # mosi $end
$var wire 1 $ done $end
$var wire 1 % cs $end
$var wire 1 & busy $end
$var reg 1 ' clk $end
$var reg 8 ( expected_rx [7:0] $end
$var reg 8 ) expected_tx [7:0] $end
$var reg 1 * miso $end
$var reg 1 + reset $end
$var reg 1 , start $end
$var reg 8 - tx_data [7:0] $end
$var integer 32 . errors [31:0] $end
$var integer 32 / i [31:0] $end
$scope module uut $end
$var wire 1 ' clk $end
$var wire 1 * miso $end
$var wire 1 + reset $end
$var wire 1 , start $end
$var wire 8 0 tx_data [7:0] $end
$var reg 3 1 bit_count [2:0] $end
$var reg 1 & busy $end
$var reg 1 % cs $end
$var reg 1 $ done $end
$var reg 1 # mosi $end
$var reg 8 2 rx_data [7:0] $end
$var reg 8 3 rx_shift [7:0] $end
$var reg 1 ! sclk $end
$var reg 8 4 tx_shift [7:0] $end
$upscope $end
$upscope $end
$enddefinitions $end
$comment Show the parameter values. $end
$dumpall
$end
#0
$dumpvars
bx 4
bx 3
bx 2
bx 1
b0 0
bx /
b0 .
b0 -
0,
1+
0*
bx )
bx (
0'
x&
x%
x$
x#
bx "
x!
$end
#5000
0$
0&
1%
0!
0#
b0 1
b0 "
b0 2
b0 3
b0 4
1'
#6000
1,
b10110010 -
b10110010 0
b1100101 (
b10110010 )
0+
#10000
0'
#15000
1&
0%
b10110010 4
1'
#16000
1*
b0 /
0,
#20000
0'
#25000
b10000000 3
1!
1'
#26000
0*
b1 /
#30000
0'
#35000
1#
b1011001 4
b1 1
0!
1'
#40000
0'
#45000
b1000000 3
1!
1'
#46000
1*
b10 /
#50000
0'
#55000
0#
b101100 4
b10 1
0!
1'
#60000
0'
#65000
b10100000 3
1!
1'
#66000
0*
b11 /
#70000
0'
#75000
b10110 4
b11 1
0!
1'
#80000
0'
#85000
b1010000 3
1!
1'
#86000
b100 /
#90000
0'
#95000
1#
b1011 4
b100 1
0!
1'
#100000
0'
#105000
b101000 3
1!
1'
#106000
1*
b101 /
#110000
0'
#115000
b101 4
b101 1
0!
1'
#120000
0'
#125000
b10010100 3
1!
1'
#126000
b110 /
#130000
0'
#135000
0#
b10 4
b110 1
0!
1'
#140000
0'
#145000
b11001010 3
1!
1'
#146000
0*
b111 /
#150000
0'
#155000
1#
b1 4
b111 1
0!
1'
#160000
0'
#165000
b1100101 3
1!
1'
#166000
b1000 /
#170000
0'
#175000
0#
1$
0&
1%
b110010 "
b110010 2
0!
1'
#176000
b1 .
