Peripheral-Configuration-Distribution-Controller/rtl/sipo.v
module sipo (
    input  wire       clk,
    input  wire       reset,
    input  wire       enable,
    input  wire       serial_in,
    output reg  [7:0] parallel_out,
    output reg        valid
);

    reg [7:0] shift_reg;
    reg [2:0] bit_count;

    always @(posedge clk) begin

        if (reset) begin
            shift_reg   <= 8'b0;
            parallel_out <= 8'b0;
            bit_count   <= 3'b0;
            valid       <= 1'b0;
        end

        else begin

            valid <= 1'b0;

            if (enable) begin

                if (bit_count < 3'd7) begin
                    shift_reg <= {serial_in, shift_reg[7:1]};
                    bit_count <= bit_count + 1'b1;
                end

                else begin
                    shift_reg <= {serial_in, shift_reg[7:1]};

                    parallel_out <= {serial_in, shift_reg[7:1]};

                    bit_count <= 3'b0;
                    valid <= 1'b1;
                end

            end

        end

    end

endmodule

Peripheral-Configuration-Distribution-Controller/rtl/piso.v
module piso (
    input wire       clk,
    input wire       reset,
    input wire       load,
    input wire       enable,

    input wire [7:0] parallel_in,

    output reg       serial_out,
    output reg       valid
);

    reg [7:0] shift_reg;
    reg [2:0] bit_count;

    always @(posedge clk) begin

        if (reset) begin

            shift_reg  <= 8'b0;
            bit_count  <= 3'b0;
            serial_out <= 1'b0;
            valid      <= 1'b0;

        end

        else begin

            valid <= 1'b0;

            // Load parallel data
            if (load) begin

                shift_reg  <= parallel_in;
                bit_count  <= 3'b0;
                serial_out <= parallel_in[0];

            end

            // Shift only when enabled
            else if (enable) begin

                if (bit_count < 3'd7) begin

                    shift_reg  <= shift_reg >> 1;
                    bit_count  <= bit_count + 1'b1;
                    serial_out <= shift_reg[1];

                end

                else begin

                    shift_reg  <= shift_reg >> 1;
                    bit_count  <= 3'b0;
                    serial_out <= shift_reg[7];
                    valid      <= 1'b1;

                end

            end

        end

    end

endmodule

Peripheral-Configuration-Distribution-Controller/rtl/clock_divider.v
module clock_divider (
    input  wire clk,
    input  wire reset,
    output reg  clk_out
);

    reg [1:0] count;

    always @(posedge clk) begin

        if (reset) begin
            count   <= 2'b00;
            clk_out <= 1'b0;
        end

        else begin

            if (count == 2'd1) begin
                count   <= 2'b00;
                clk_out <= ~clk_out;
            end

            else begin
                count <= count + 1'b1;
            end

        end

    end

endmodule

Peripheral-Configuration-Distribution-Controller/rtl/spi_master_top.v
module spi_master_top (
    input wire        clk,
    input wire        reset,
    input wire        start,
    input wire [7:0]  tx_data,
    input wire        miso,

    output wire       mosi,
    output reg        sclk,
    output wire       cs,
    output wire [7:0] rx_data,
    output wire       busy,
    output wire       done
);

    // ============================================================
    // Internal signals
    // ============================================================

    wire spi_clk;

    wire piso_serial;
    wire piso_valid;

    wire [7:0] sipo_parallel;
    wire       sipo_valid;

    reg piso_load;
    reg piso_enable;
    reg sipo_enable;

    reg [2:0] bit_count;

    reg active;
    reg done_reg;

    reg spi_clk_prev;

    // First rising edge must occur before PISO is shifted.
    reg first_sample_done;

    // ============================================================
    // Clock divider
    // ============================================================

    clock_divider clk_div (
        .clk(clk),
        .reset(reset),
        .clk_out(spi_clk)
    );

    // ============================================================
    // PISO
    // ============================================================

    piso tx_piso (
        .clk(clk),
        .reset(reset),
        .load(piso_load),
        .enable(piso_enable),
        .parallel_in(tx_data),
        .serial_out(piso_serial),
        .valid(piso_valid)
    );

    // ============================================================
    // SIPO
    // ============================================================

    sipo rx_sipo (
        .clk(clk),
        .reset(reset),
        .enable(sipo_enable),
        .serial_in(miso),
        .parallel_out(sipo_parallel),
        .valid(sipo_valid)
    );

    // ============================================================
    // Outputs
    // ============================================================

    assign mosi    = piso_serial;
    assign rx_data = sipo_parallel;

    assign busy = active;
    assign cs   = ~active;
    assign done = done_reg;

    // ============================================================
    // SPI controller
    // ============================================================

    always @(posedge clk) begin

        if (reset) begin

            piso_load       <= 1'b0;
            piso_enable     <= 1'b0;
            sipo_enable     <= 1'b0;

            bit_count       <= 3'd0;

            active          <= 1'b0;
            done_reg        <= 1'b0;

            spi_clk_prev    <= 1'b0;
            first_sample_done <= 1'b0;

            sclk            <= 1'b0;

        end

        else begin

            // ----------------------------------------------------
            // Default pulse signals
            // ----------------------------------------------------

            piso_load   <= 1'b0;
            piso_enable <= 1'b0;
            sipo_enable <= 1'b0;

            done_reg <= 1'b0;

            // ----------------------------------------------------
            // Start transaction
            // ----------------------------------------------------

            if (start && !active) begin

                // Load TX data into PISO.
                piso_load <= 1'b1;

                bit_count <= 3'd0;

                active <= 1'b1;

                sclk <= 1'b0;

                /*
                 * Synchronize the divider edge detector with its
                 * current state.
                 */
                spi_clk_prev <= spi_clk;

                /*
                 * Most important part:
                 * do not shift PISO until the first rising edge
                 * has sampled bit 0.
                 */
                first_sample_done <= 1'b0;

            end

            // ----------------------------------------------------
            // Active SPI transaction
            // ----------------------------------------------------

            else if (active) begin

                // Detect divider clock transition.
                if (spi_clk != spi_clk_prev) begin

                    // =================================================
                    // RISING EDGE
                    // =================================================

                    if (spi_clk == 1'b1) begin

                        /*
                         * Sample MISO.
                         *
                         * This is always the first SPI operation.
                         * Therefore PISO bit 0 cannot be lost.
                         */
                        sipo_enable <= 1'b1;

                        sclk <= 1'b1;

                        first_sample_done <= 1'b1;

                    end

                    // =================================================
                    // FALLING EDGE
                    // =================================================

                    else begin

                        sclk <= 1'b0;

                        /*
                         * Never shift before the first rising edge.
                         */
                        if (first_sample_done) begin

                            if (bit_count == 3'd7) begin

                                // Eight bits completed.
                                active   <= 1'b0;
                                done_reg <= 1'b1;

                            end

                            else begin

                                // Prepare next TX bit.
                                piso_enable <= 1'b1;

                                bit_count <= bit_count + 1'b1;

                            end

                        end

                    end

                end

                // Update divider history.
                spi_clk_prev <= spi_clk;

            end

            else begin

                sclk <= 1'b0;

            end

        end

    end

endmodule

Peripheral-Configuration-Distribution-Controller/tb/spi_master_top_tb.v
`timescale 1ns/1ps

module spi_master_top_tb;

    reg clk;
    reg reset;
    reg start;

    reg [7:0] tx_data;
    reg miso;

    wire mosi;
    wire sclk;
    wire cs;

    wire [7:0] rx_data;
    wire busy;
    wire done;

    reg [7:0] slave_tx_data;
    reg [7:0] slave_rx_data;

    integer bit_count;
    integer errors;


    // ------------------------------------------------------------
    // DUT
    // ------------------------------------------------------------

    spi_master_top uut (
        .clk     (clk),
        .reset   (reset),
        .start   (start),

        .tx_data (tx_data),
        .miso    (miso),

        .mosi    (mosi),
        .sclk    (sclk),
        .cs      (cs),

        .rx_data (rx_data),
        .busy    (busy),
        .done    (done)
    );


    // ------------------------------------------------------------
    // CPU clock
    // ------------------------------------------------------------

    always #5 clk = ~clk;


    // ------------------------------------------------------------
    // Simulated SPI slave
    //
    // LSB first
    // ------------------------------------------------------------

    always @(negedge sclk) begin

        if (!cs) begin
            miso <= slave_tx_data[bit_count];
        end

    end


    // ------------------------------------------------------------
    // Slave receives MOSI
    // ------------------------------------------------------------

    always @(posedge sclk) begin

        if (!cs) begin

            slave_rx_data[bit_count] = mosi;

            if (bit_count < 7)
                bit_count = bit_count + 1;
            else
                bit_count = 0;

        end

    end


    // ------------------------------------------------------------
    // Test
    // ------------------------------------------------------------

    initial begin

        $dumpfile("sim/waves/spi_master_top.vcd");
        $dumpvars(0, spi_master_top_tb);

        clk           = 1'b0;
        reset         = 1'b1;
        start         = 1'b0;

        tx_data       = 8'b0;
        miso          = 1'b0;

        slave_tx_data = 8'b01100101;
        slave_rx_data = 8'b0;

        bit_count     = 0;
        errors        = 0;


        // --------------------------------------------------------
        // Reset
        // --------------------------------------------------------

        #20;

        reset = 1'b0;


        // --------------------------------------------------------
        // Prepare transaction
        // --------------------------------------------------------

        tx_data = 8'b10100101;

        // Preload first MISO bit
        miso = slave_tx_data[0];

        #10;

        start = 1'b1;

        @(posedge clk);
        #1;

        start = 1'b0;


        // --------------------------------------------------------
        // Check transaction started
        // --------------------------------------------------------

        if (busy !== 1'b1) begin

            $display("ERROR: SPI transaction did not start");
            errors = errors + 1;

        end
        else begin

            $display("PASS: SPI transaction started");

        end


        if (cs !== 1'b0) begin

            $display("ERROR: CS not asserted");
            errors = errors + 1;

        end
        else begin

            $display("PASS: CS asserted");

        end


        // --------------------------------------------------------
        // Wait for transaction completion
        // --------------------------------------------------------

        wait(done == 1'b1);

        #5;


        // --------------------------------------------------------
        // Check RX
        // --------------------------------------------------------

        if (rx_data !== slave_tx_data) begin

            $display(
                "ERROR: RX DATA | Expected=%b | Got=%b",
                slave_tx_data,
                rx_data
            );

            errors = errors + 1;

        end
        else begin

            $display("PASS: Correct RX data received");

        end


        // --------------------------------------------------------
        // Check TX
        // --------------------------------------------------------

        if (slave_rx_data !== tx_data) begin

            $display(
                "ERROR: TX DATA | Expected=%b | Got=%b",
                tx_data,
                slave_rx_data
            );

            errors = errors + 1;

        end
        else begin

            $display("PASS: Correct TX data transmitted");

        end


        // --------------------------------------------------------
        // Check BUSY
        // --------------------------------------------------------

        if (busy !== 1'b0) begin

            $display("ERROR: BUSY did not deassert");
            errors = errors + 1;

        end
        else begin

            $display("PASS: BUSY deasserted");

        end


        // --------------------------------------------------------
        // Check CS
        // --------------------------------------------------------

        if (cs !== 1'b1) begin

            $display("ERROR: CS did not deassert");
            errors = errors + 1;

        end
        else begin

            $display("PASS: CS deasserted");

        end


        // --------------------------------------------------------
        // Final result
        // --------------------------------------------------------

        if (errors == 0) begin

            $display("--------------------------------");
            $display("SPI MASTER TOP TEST PASSED");
            $display("--------------------------------");

        end
        else begin

            $display("--------------------------------");
            $display(
                "SPI MASTER TOP TEST FAILED: %0d errors",
                errors
            );
            $display("--------------------------------");

        end

        $finish;

    end

endmodule

Peripheral-Configuration-Distribution-Controller/sim/waves/spi_master_top.vcd
$date
	Fri Oct  2 00:15:15 2026
$end
$version
	Icarus Verilog
$end
$timescale
	1ps
$end
$scope module spi_master_top_tb $end
$var wire 1 ! sclk $end
$var wire 8 " rx_data [7:0] $end
$var wire 1 # mosi $end
$var wire 1 $ done $end
$var wire 1 % cs $end
$var wire 1 & busy $end
$var reg 1 ' clk $end
$var reg 1 ( miso $end
$var reg 1 ) reset $end
$var reg 8 * slave_rx_data [7:0] $end
$var reg 8 + slave_tx_data [7:0] $end
$var reg 1 , start $end
$var reg 8 - tx_data [7:0] $end
$var integer 32 . bit_count [31:0] $end
$var integer 32 / errors [31:0] $end
$scope module uut $end
$var wire 1 & busy $end
$var wire 1 ' clk $end
$var wire 1 % cs $end
$var wire 1 $ done $end
$var wire 1 ( miso $end
$var wire 1 # mosi $end
$var wire 1 ) reset $end
$var wire 8 0 rx_data [7:0] $end
$var wire 1 , start $end
$var wire 8 1 tx_data [7:0] $end
$var wire 1 2 spi_clk $end
$var wire 1 3 sipo_valid $end
$var wire 8 4 sipo_parallel [7:0] $end
$var wire 1 5 piso_valid $end
$var wire 1 6 piso_serial $end
$var reg 1 7 active $end
$var reg 3 8 bit_count [2:0] $end
$var reg 1 9 done_reg $end
$var reg 1 : first_sample_done $end
$var reg 1 ; piso_enable $end
$var reg 1 < piso_load $end
$var reg 1 ! sclk $end
$var reg 1 = sipo_enable $end
$var reg 1 > spi_clk_prev $end
$scope module clk_div $end
$var wire 1 ' clk $end
$var wire 1 ) reset $end
$var reg 1 2 clk_out $end
$var reg 2 ? count [1:0] $end
$upscope $end
$scope module rx_sipo $end
$var wire 1 ' clk $end
$var wire 1 = enable $end
$var wire 1 ) reset $end
$var wire 1 ( serial_in $end
$var reg 3 @ bit_count [2:0] $end
$var reg 8 A parallel_out [7:0] $end
$var reg 8 B shift_reg [7:0] $end
$var reg 1 3 valid $end
$upscope $end
$scope module tx_piso $end
$var wire 1 ' clk $end
$var wire 1 ; enable $end
$var wire 1 < load $end
$var wire 8 C parallel_in [7:0] $end
$var wire 1 ) reset $end
$var reg 3 D bit_count [2:0] $end
$var reg 1 6 serial_out $end
$var reg 8 E shift_reg [7:0] $end
$var reg 1 5 valid $end
$upscope $end
$upscope $end
$upscope $end
$enddefinitions $end
$comment Show the parameter values. $end
$dumpall
$end
#0
$dumpvars
bx E
bx D
b0 C
bx B
bx A
bx @
bx ?
x>
x=
x<
x;
x:
x9
bx 8
x7
x6
x5
bx 4
x3
x2
b0 1
bx 0
b0 /
b0 .
b0 -
0,
b1100101 +
b0 *
1)
0(
0'
x&
x%
x$
x#
bx "
x!
$end
#5000
1%
02
b0 ?
05
0#
06
b0 D
b0 E
03
b0 @
b0 "
b0 0
b0 4
b0 A
b0 B
0!
0:
0>
0$
09
0&
07
b0 8
0=
0;
0<
1'
#10000
0'
#15000
1'
#20000
0'
1(
b10100101 -
b10100101 1
b10100101 C
0)
#25000
b1 ?
1'
#30000
0'
1,
#35000
0%
1&
17
1<
12
b0 ?
1'
#36000
0,
#40000
0'
#45000
b1 .
b1 *
b1 ?
1#
16
b10100101 E
1>
1:
1!
1=
0<
1'
#50000
0'
#55000
0=
b1 @
b10000000 B
02
b0 ?
1'
#60000
0'
#65000
0(
b1 ?
0>
b1 8
1;
0!
1'
#70000
0'
#75000
0;
0#
06
b1 D
b1010010 E
12
b0 ?
1'
#80000
0'
#85000
b10 .
b1 ?
1>
1!
1=
1'
#90000
0'
#95000
0=
b10 @
b1000000 B
02
b0 ?
1'
#100000
0'
#105000
1(
b1 ?
0>
b10 8
1;
0!
1'
#110000
0'
#115000
0;
1#
16
b10 D
b101001 E
12
b0 ?
1'
#120000
0'
#125000
b11 .
b101 *
b1 ?
1>
1!
1=
1'
#130000
0'
#135000
0=
b11 @
b10100000 B
02
b0 ?
1'
#140000
0'
#145000
0(
b1 ?
0>
b11 8
1;
0!
1'
#150000
0'
#155000
0;
0#
06
b11 D
b10100 E
12
b0 ?
1'
#160000
0'
#165000
b100 .
b1 ?
1>
1!
1=
1'
#170000
0'
#175000
0=
b100 @
b1010000 B
02
b0 ?
1'
#180000
0'
#185000
b1 ?
0>
b100 8
1;
0!
1'
#190000
0'
#195000
0;
b100 D
b1010 E
12
b0 ?
1'
#200000
0'
#205000
b101 .
b1 ?
1>
1!
1=
1'
#210000
0'
#215000
0=
b101 @
b101000 B
02
b0 ?
1'
#220000
0'
#225000
1(
b1 ?
0>
b101 8
1;
0!
1'
#230000
0'
#235000
0;
1#
16
b101 D
b101 E
12
b0 ?
1'
#240000
0'
#245000
b110 .
b100101 *
b1 ?
1>
1!
1=
1'
#250000
0'
#255000
0=
b110 @
b10010100 B
02
b0 ?
1'
#260000
0'
#265000
b1 ?
0>
b110 8
1;
0!
1'
#270000
0'
#275000
0;
0#
06
b110 D
b10 E
12
b0 ?
1'
#280000
0'
#285000
b111 .
b1 ?
1>
1!
1=
1'
#290000
0'
#295000
0=
b111 @
b11001010 B
02
b0 ?
1'
#300000
0'
#305000
0(
b1 ?
0>
b111 8
1;
0!
1'
#310000
0'
#315000
0;
1#
16
b111 D
b1 E
12
b0 ?
1'
#320000
0'
#325000
b0 .
b10100101 *
b1 ?
1>
1!
1=
1'
#330000
0'
#335000
0=
13
b0 @
b1100101 "
b1100101 0
b1100101 4
b1100101 A
b1100101 B
02
b0 ?
1'
#340000
0'
#345000
1(
1%
b1 ?
03
0>
1$
19
0&
07
0!
1'
